Workbook
Name Slicer_Item: #N/A
Name Slicer_Month: #N/A
Name Slicer_Month1: #N/A
Name Slicer_Month2: #N/A
Name Slicer_Spent_Group: #N/A

Sheet dirty_cafe_sales_raw
A1: Transaction ID | B1: Item | C1: Quantity | D1: Price Per Unit | E1: Total Spent | F1: Payment Method | G1: Location | H1: Transaction Date
A2: TXN_1961373 | B2: Coffee | C2: 2 | D2: 2 | E2: 4 | F2: Credit Card | G2: Takeaway | H2: 45177
A3: TXN_4977031 | B3: Cake | C3: 4 | D3: 3 | E3: 12 | F3: Cash | G3: In-store | H3: 45062
A4: TXN_4271903 | B4: Cookie | C4: 4 | D4: 1 | E4: ERROR | F4: Credit Card | G4: In-store | H4: 45126
A5: TXN_7034554 | B5: Salad | C5: 2 | D5: 5 | E5: 10 | F5: UNKNOWN | G5: UNKNOWN | H5: 45043
A6: TXN_3160411 | B6: Coffee | C6: 2 | D6: 2 | E6: 4 | F6: Digital Wallet | G6: In-store | H6: 45088
A7: TXN_2602893 | B7: Smoothie | C7: 5 | D7: 4 | E7: 20 | F7: Credit Card | H7: 45016
A8: TXN_4433211 | B8: UNKNOWN | C8: 3 | D8: 3 | E8: 9 | F8: ERROR | G8: Takeaway | H8: 45205
A9: TXN_6699534 | B9: Sandwich | C9: 4 | D9: 4 | E9: 16 | F9: Cash | G9: UNKNOWN | H9: 45227
A10: TXN_4717867 | C10: 5 | D10: 3 | E10: 15 | G10: Takeaway | H10: 45135
A11: TXN_2064365 | B11: Sandwich | C11: 5 | D11: 4 | E11: 20 | G11: In-store | H11: 45291
A12: TXN_2548360 | B12: Salad | C12: 5 | D12: 5 | E12: 25 | F12: Cash | G12: Takeaway | H12: 45237
A13: TXN_3051279 | B13: Sandwich | C13: 2 | D13: 4 | E13: 8 | F13: Credit Card | G13: Takeaway | H13: ERROR
A14: TXN_7619095 | B14: Sandwich | C14: 2 | D14: 4 | E14: 8 | F14: Cash | G14: In-store | H14: 45049
A15: TXN_9437049 | B15: Cookie | C15: 5 | D15: 1 | E15: 5 | G15: Takeaway | H15: 45078
A16: TXN_8915701 | B16: ERROR | C16: 2 | D16: 1.5 | E16: 3 | G16: In-store | H16: 45006
A17: TXN_2847255 | B17: Salad | C17: 3 | D17: 5 | E17: 15 | F17: Credit Card | G17: In-store | H17: 45245
A18: TXN_3765707 | B18: Sandwich | C18: 1 | D18: 4 | E18: 4 | H18: 45087
A19: TXN_6769710 | B19: Juice | C19: 2 | D19: 3 | E19: 6 | F19: Cash | G19: In-store | H19: 44981
A20: TXN_8876618 | B20: Cake | C20: 5 | D20: 3 | E20: 15 | F20: Cash | G20: ERROR | H20: 45010
A21: TXN_3709394 | B21: Juice | C21: 4 | D21: 3 | E21: 12 | F21: Cash | G21: Takeaway | H21: 44941
A22: TXN_3522028 | B22: Smoothie | C22: ERROR | D22: 4 | E22: 20 | F22: Cash | G22: In-store | H22: 45020
A23: TXN_3567645 | B23: Smoothie | C23: 4 | D23: 4 | E23: 16 | F23: Credit Card | G23: Takeaway | H23: 45015
A24: TXN_5132361 | B24: Sandwich | C24: 3 | D24: 4 | E24: 12 | F24: Digital Wallet | G24: Takeaway | H24: 45261
A25: TXN_2616390 | B25: Sandwich | C25: 2 | D25: 4 | E25: 8 | H25: 45187
A26: TXN_9400181 | B26: Sandwich | C26: 5 | D26: 4 | E26: 20 | F26: Cash | G26: In-store | H26: 45080
A27: TXN_7958992 | B27: Smoothie | C27: 3 | D27: 4 | F27: UNKNOWN | G27: UNKNOWN | H27: 45273
A28: TXN_5183041 | B28: Cookie | C28: 5 | D28: 1 | E28: 5 | F28: Credit Card | G28: In-store | H28: 45036
A29: TXN_5695074 | B29: Juice | C29: 4 | D29: 3 | E29: 12 | F29: Credit Card | G29: Takeaway | H29: 45026
A30: TXN_8467949 | B30: Smoothie | C30: 5 | D30: 4 | E30: 20 | F30: Credit Card | H30: 44996
A31: TXN_7640952 | B31: Cake | C31: 4 | D31: 3 | E31: 12 | F31: Digital Wallet | G31: Takeaway | H31: ERROR
A32: TXN_1736287 | C32: 5 | D32: 2 | E32: 10 | F32: Digital Wallet | H32: 45079
A33: TXN_8927252 | B33: UNKNOWN | C33: 2 | D33: 1 | E33: ERROR | F33: Credit Card | G33: ERROR | H33: 45236
A34: TXN_9677376 | B34: Smoothie | C34: 4 | D34: 4 | E34: 16 | G34: In-store | H34: 45153
A35: TXN_7710508 | B35: UNKNOWN | C35: 5 | D35: 1 | E35: 5 | F35: Cash | H35: ERROR
A36: TXN_8853997 | B36: Smoothie | C36: 2 | D36: 4 | E36: 8 | F36: Digital Wallet | G36: Takeaway | H36: 45208
A37: TXN_9130559 | B37: Sandwich | C37: 1 | D37: 4 | E37: 4 | F37: Credit Card | G37: UNKNOWN | H37: 45074
A38: TXN_6855453 | B38: UNKNOWN | C38: 4 | D38: 3 | E38: 12 | G38: In-store | H38: 45124
A39: TXN_1080432 | B39: Salad | C39: 2 | D39: 5 | E39: 10 | F39: Credit Card | G39: In-store | H39: 45045
A40: TXN_2655815 | B40: Smoothie | C40: 4 | D40: 4 | E40: 16 | G40: Takeaway | H40: 45085
A41: TXN_6688524 | B41: Coffee | C41: 4 | D41: 2 | E41: 8 | F41: ERROR | H41: 45106
A42: TXN_2083138 | B42: Smoothie | C42: 3 | D42: 4 | E42: 12 | G42: In-store | H42: 45033
A43: TXN_2427584 | B43: Sandwich | C43: 4 | D43: 4 | E43: 16 | G43: Takeaway | H43: 45282
A44: TXN_6650263 | B44: Tea | C44: 2 | D44: 1.5 | E44: UNKNOWN | G44: Takeaway | H44: 44936
A45: TXN_9620080 | B45: Juice | C45: 4 | D45: 3 | E45: 12 | G45: Takeaway | H45: 45201
A46: TXN_1491578 | B46: Cookie | C46: 2 | D46: 1 | E46: 2 | H46: 44980
A47: TXN_5455792 | B47: Salad | C47: 3 | D47: 5 | E47: 15 | F47: Cash | H47: 45007
A48: TXN_8078640 | B48: Juice | C48: 4 | D48: 3 | E48: 12 | F48: Digital Wallet | G48: In-store | H48: 45233
A49: TXN_9499313 | B49: Juice | C49: 5 | D49: 3 | E49: 15 | H49: 44987
A50: TXN_8201146 | B50: Juice | C50: 5 | D50: 3 | E50: 15 | F50: Cash | H50: 45103
A51: TXN_8230936 | B51: Cake | C51: 3 | D51: 3 | E51: 9 | G51: ERROR | H51: 45048
A52: TXN_7742742 | B52: Cake | C52: 5 | D52: 3 | E52: 15 | G52: Takeaway | H52: 45174
A53: TXN_6342161 | B53: Salad | C53: 5 | D53: 5 | E53: 25 | F53: ERROR | G53: Takeaway | H53: 44934
A54: TXN_8914892 | B54: UNKNOWN | C54: 5 | D54: 5 | E54: 25 | F54: Digital Wallet | H54: 45000
A55: TXN_3363746 | B55: Smoothie | C55: 3 | D55: 4 | E55: 12 | F55: Credit Card | H55: 45255
A56: TXN_8614868 | B56: Smoothie | C56: 5 | D56: 4 | E56: 20 | F56: Digital Wallet | G56: Takeaway | H56: 45265
A57: TXN_5522862 | B57: Cookie | C57: ERROR | D57: 1 | E57: 2 | F57: Credit Card | G57: Takeaway | H57: 45004
A58: TXN_3578141 | B58: Cake | C58: 5 | E58: 15 | G58: Takeaway | H58: 45104
A59: TXN_2080895 | B59: Cake | C59: UNKNOWN | D59: 3 | E59: 3 | F59: Digital Wallet | G59: In-store | H59: 45035
A60: TXN_6421134 | B60: Sandwich | C60: 4 | D60: 4 | E60: 16 | F60: Cash | G60: Takeaway | H60: 45233
A61: TXN_8813311 | B61: Juice | C61: 5 | D61: 3 | E61: 15 | G61: In-store | H61: 45206
A62: TXN_9023317 | B62: Salad | C62: 1 | D62: 5 | E62: 5 | H62: 45199
A63: TXN_8051289 | C63: 1 | D63: 3 | E63: 3 | G63: In-store | H63: 45208
A64: TXN_2537617 | B64: Sandwich | C64: 1 | D64: 4 | E64: 4 | F64: Cash | H64: 45073
A65: TXN_9099694 | B65: UNKNOWN | C65: 3 | D65: 5 | E65: 15 | G65: Takeaway | H65: 45248
A66: TXN_9230615 | B66: Smoothie | C66: 4 | D66: 4 | E66: 16 | F66: Digital Wallet | H66: 45078
A67: TXN_4987129 | B67: Sandwich | C67: 3 | G67: In-store | H67: 45219
A68: TXN_8501819 | B68: Juice | D68: 3 | E68: 6 | F68: Cash | H68: 45015
A69: TXN_3068204 | B69: Cookie | C69: 1 | D69: 1 | E69: 1 | F69: Credit Card | G69: Takeaway | H69: 45202
A70: TXN_8427104 | B70: Salad | C70: 2 | D70: ERROR | E70: 10 | G70: In-store | H70: 45226
A71: TXN_8471743 | B71: ERROR | C71: 5 | D71: 3 | E71: 15 | F71: Digital Wallet | G71: In-store | H71: 45022
A72: TXN_2621580 | B72: Tea | C72: 2 | D72: 1.5 | E72: 3 | F72: Cash | G72: In-store | H72: 45007
A73: TXN_4726376 | B73: Cake | C73: 2 | D73: 3 | E73: 6 | F73: Credit Card | G73: In-store | H73: 44957
A74: TXN_6044979 | C74: 1 | D74: 1 | E74: 1 | F74: Cash | G74: In-store | H74: 45268
A75: TXN_4238417 | B75: Salad | C75: 2 | D75: 5 | E75: 10 | G75: ERROR | H75: 45096
A76: TXN_1900620 | B76: Smoothie | C76: 2 | D76: 4 | E76: 8 | F76: Credit Card | G76: ERROR | H76: 45274
A77: TXN_6420335 | B77: Coffee | C77: 1 | D77: 2 | E77: 2 | F77: Cash | G77: Takeaway | H77: 45123
A78: TXN_3858209 | B78: Sandwich | C78: 4 | D78: 4 | E78: 16 | F78: Cash | H78: 44979
A79: TXN_2091733 | B79: Salad | C79: 1 | D79: 5 | E79: 5 | G79: In-store
A80: TXN_8735480 | B80: Tea | C80: 5 | D80: 1.5 | E80: 7.5 | F80: Cash | H80: 45079
A81: TXN_3829165 | B81: Juice | C81: 4 | D81: 3 | E81: 12 | F81: Cash | G81: In-store | H81: 45092
A82: TXN_3748616 | B82: Coffee | C82: 2 | D82: 2 | E82: 4 | F82: Credit Card | G82: In-store | H82: 45269
A83: TXN_1993289 | B83: Sandwich | C83: 2 | D83: 4 | E83: 8 | G83: In-store | H83: 45034
A84: TXN_2123367 | B84: Cookie | C84: 2 | D84: 1 | E84: 2 | H84: 45237
A85: TXN_5266394 | B85: Cake | C85: 3 | D85: 3 | E85: 9 | F85: Cash | G85: In-store | H85: 45227
A86: TXN_5107946 | B86: Cake | C86: 4 | D86: 3 | E86: 12 | F86: Credit Card | H86: 45282
A87: TXN_8035512 | B87: Tea | C87: 3 | E87: 4.5 | F87: Cash | G87: UNKNOWN | H87: 45228
A88: TXN_8718498 | B88: Cake | C88: 5 | D88: 3 | E88: 15 | F88: Credit Card | G88: ERROR | H88: 45046
A89: TXN_3955361 | B89: Cookie | C89: 5 | D89: 1 | E89: 5 | G89: Takeaway | H89: 45018
A90: TXN_9487821 | B90: ERROR | C90: 1 | D90: 5 | E90: 5 | F90: Digital Wallet | G90: Takeaway | H90: 45070
A91: TXN_4132730 | C91: 5 | D91: 1 | E91: 5 | G91: In-store | H91: 44997
A92: TXN_8976658 | B92: Tea | C92: 2 | D92: 1.5 | E92: 3 | F92: Credit Card | G92: In-store | H92: 45154
A93: TXN_5455936 | B93: UNKNOWN | C93: 5 | D93: 3 | E93: 15 | G93: In-store | H93: 45227
A94: TXN_2725602 | B94: Juice | C94: 5 | D94: 3 | E94: 15 | F94: Credit Card | H94: 45179
A95: TXN_3011323 | B95: Coffee | C95: 3 | D95: 2 | E95: 6 | F95: Credit Card | H95: 44992
A96: TXN_6289610 | B96: Juice | C96: 3 | D96: 3 | E96: UNKNOWN | F96: Cash | G96: Takeaway | H96: 45145
A97: TXN_8268061 | B97: Salad | C97: 3 | D97: 5 | E97: 15 | F97: ERROR | G97: Takeaway | H97: 45158
A98: TXN_5220895 | B98: Salad | C98: 5 | D98: 5 | E98: 25 | F98: Cash | G98: In-store | H98: 45087
A99: TXN_3085509 | B99: Coffee | C99: 4 | D99: 2 | E99: 8 | F99: Digital Wallet | G99: In-store | H99: 45031
A100: TXN_9999113 | B100: Juice | C100: 4 | D100: 3 | E100: 12 | F100: Cash | G100: Takeaway | H100: 45073
...

Sheet Working Sheet
A1: Item | B1: Quantity | C1: Price Per Unit | D1: Total Spent | E1: Spent Group | F1: Payment Method | G1: Location | H1: Transaction Date | I1: Year | J1: Month | K1: Day | L1: Days of the week | M1: Transcation Complete?
A2: Salad | B2: =$D2/$C2 -> 2 | C2: 5 | D2: 10 | E2: {=_xlfn.IFS(D2<=5, "$1-5", D2<=10, "$6-10",D2<=15,"$11-15", D2<=20, "$16-20", D2>20, "$20+")} -> $6-10 | F2: Unspecified | G2: Unspecified | H2: 44927 | I2: =IFERROR(YEAR(H2), "N/A") -> 2023 | J2: {=IFERROR(TEXT(H2, "[$-en-US]mmm"), _xleta.N/A)} -> Jan | K2: =IFERROR(DAY(H2), "N/A") -> 1 | L2: =IFERROR(TEXT(K2, "[$-en-US]dddd"), "N/A") -> Sunday | M2: =IF(AND(H2="Error",F2="Error"), "No","Yes") -> Yes
A3: Cake | B3: =$D3/$C3 -> 3 | C3: 3 | D3: 9 | E3: {=_xlfn.IFS(D3<=5, "$1-5", D3<=10, "$6-10",D3<=15,"$11-15", D3<=20, "$16-20", D3>20, "$20+")} -> $6-10 | F3: Error | G3: In-store | H3: 44927 | I3: =IFERROR(YEAR(H3), "N/A") -> 2023 | J3: {=IFERROR(TEXT(H3, "[$-en-US]mmm"), _xleta.N/A)} -> Jan | K3: =IFERROR(DAY(H3), "N/A") -> 1 | L3: =IFERROR(TEXT(K3, "[$-en-US]dddd"), "N/A") -> Sunday | M3: =IF(AND(H3="Error",F3="Error"), "No","Yes") -> Yes
A4: Sandwich | B4: 5 | C4: =$D4/$B4 -> 4 | D4: 20 | E4: {=_xlfn.IFS(D4<=5, "$1-5", D4<=10, "$6-10",D4<=15,"$11-15", D4<=20, "$16-20", D4>20, "$20+")} -> $16-20 | F4: Digital Wallet | G4: In-store | H4: 44927 | I4: =IFERROR(YEAR(H4), "N/A") -> 2023 | J4: {=IFERROR(TEXT(H4, "[$-en-US]mmm"), _xleta.N/A)} -> Jan | K4: =IFERROR(DAY(H4), "N/A") -> 1 | L4: =IFERROR(TEXT(K4, "[$-en-US]dddd"), "N/A") -> Sunday | M4: =IF(AND(H4="Error",F4="Error"), "No","Yes") -> Yes
A5: Juice | B5: 5 | C5: 3 | D5: 15 | E5: {=_xlfn.IFS(D5<=5, "$1-5", D5<=10, "$6-10",D5<=15,"$11-15", D5<=20, "$16-20", D5>20, "$20+")} -> $11-15 | F5: Digital Wallet | G5: Takeaway | H5: 44927 | I5: =IFERROR(YEAR(H5), "N/A") -> 2023 | J5: {=IFERROR(TEXT(H5, "[$-en-US]mmm"), _xleta.N/A)} -> Jan | K5: =IFERROR(DAY(H5), "N/A") -> 1 | L5: =IFERROR(TEXT(K5, "[$-en-US]dddd"), "N/A") -> Sunday | M5: =IF(AND(H5="Error",F5="Error"), "No","Yes") -> Yes
A6: Sandwich | B6: 5 | C6: 4 | D6: 20 | E6: {=_xlfn.IFS(D6<=5, "$1-5", D6<=10, "$6-10",D6<=15,"$11-15", D6<=20, "$16-20", D6>20, "$20+")} -> $16-20 | F6: Cash | G6: In-store | H6: 44927 | I6: =IFERROR(YEAR(H6), "N/A") -> 2023 | J6: {=IFERROR(TEXT(H6, "[$-en-US]mmm"), _xleta.N/A)} -> Jan | K6: =IFERROR(DAY(H6), "N/A") -> 1 | L6: =IFERROR(TEXT(K6, "[$-en-US]dddd"), "N/A") -> Sunday | M6: =IF(AND(H6="Error",F6="Error"), "No","Yes") -> Yes
A7: Tea | B7: 3 | C7: 1.5 | D7: 4.5 | E7: {=_xlfn.IFS(D7<=5, "$1-5", D7<=10, "$6-10",D7<=15,"$11-15", D7<=20, "$16-20", D7>20, "$20+")} -> $1-5 | F7: Digital Wallet | G7: In-store | H7: 44927 | I7: =IFERROR(YEAR(H7), "N/A") -> 2023 | J7: {=IFERROR(TEXT(H7, "[$-en-US]mmm"), _xleta.N/A)} -> Jan | K7: =IFERROR(DAY(H7), "N/A") -> 1 | L7: =IFERROR(TEXT(K7, "[$-en-US]dddd"), "N/A") -> Sunday | M7: =IF(AND(H7="Error",F7="Error"), "No","Yes") -> Yes
A8: Salad | B8: 2 | C8: 5 | D8: 10 | E8: {=_xlfn.IFS(D8<=5, "$1-5", D8<=10, "$6-10",D8<=15,"$11-15", D8<=20, "$16-20", D8>20, "$20+")} -> $6-10 | F8: Digital Wallet | G8: Takeaway | H8: 44927 | I8: =IFERROR(YEAR(H8), "N/A") -> 2023 | J8: {=IFERROR(TEXT(H8, "[$-en-US]mmm"), _xleta.N/A)} -> Jan | K8: =IFERROR(DAY(H8), "N/A") -> 1 | L8: =IFERROR(TEXT(K8, "[$-en-US]dddd"), "N/A") -> Sunday | M8: =IF(AND(H8="Error",F8="Error"), "No","Yes") -> Yes
A9: Coffee | B9: 5 | C9: 2 | D9: 10 | E9: {=_xlfn.IFS(D9<=5, "$1-5", D9<=10, "$6-10",D9<=15,"$11-15", D9<=20, "$16-20", D9>20, "$20+")} -> $6-10 | F9: Digital Wallet | G9: Error | H9: 44927 | I9: =IFERROR(YEAR(H9), "N/A") -> 2023 | J9: {=IFERROR(TEXT(H9, "[$-en-US]mmm"), _xleta.N/A)} -> Jan | K9: =IFERROR(DAY(H9), "N/A") -> 1 | L9: =IFERROR(TEXT(K9, "[$-en-US]dddd"), "N/A") -> Sunday | M9: =IF(AND(H9="Error",F9="Error"), "No","Yes") -> Yes
A10: Unspecified | B10: 4 | C10: 3 | D10: 12 | E10: {=_xlfn.IFS(D10<=5, "$1-5", D10<=10, "$6-10",D10<=15,"$11-15", D10<=20, "$16-20", D10>20, "$20+")} -> $11-15 | F10: Unspecified | G10: Unspecified | H10: 44927 | I10: =IFERROR(YEAR(H10), "N/A") -> 2023 | J10: {=IFERROR(TEXT(H10, "[$-en-US]mmm"), _xleta.N/A)} -> Jan | K10: =IFERROR(DAY(H10), "N/A") -> 1 | L10: =IFERROR(TEXT(K10, "[$-en-US]dddd"), "N/A") -> Sunday | M10: =IF(AND(H10="Error",F10="Error"), "No","Yes") -> Yes
A11: Sandwich | B11: 1 | C11: 4 | D11: 4 | E11: {=_xlfn.IFS(D11<=5, "$1-5", D11<=10, "$6-10",D11<=15,"$11-15", D11<=20, "$16-20", D11>20, "$20+")} -> $1-5 | F11: Digital Wallet | G11: In-store | H11: 44927 | I11: =IFERROR(YEAR(H11), "N/A") -> 2023 | J11: {=IFERROR(TEXT(H11, "[$-en-US]mmm"), _xleta.N/A)} -> Jan | K11: =IFERROR(DAY(H11), "N/A") -> 1 | L11: =IFERROR(TEXT(K11, "[$-en-US]dddd"), "N/A") -> Sunday | M11: =IF(AND(H11="Error",F11="Error"), "No","Yes") -> Yes
A12: Cake | B12: 4 | C12: 3 | D12: 12 | E12: {=_xlfn.IFS(D12<=5, "$1-5", D12<=10, "$6-10",D12<=15,"$11-15", D12<=20, "$16-20", D12>20, "$20+")} -> $11-15 | F12: Cash | G12: Takeaway | H12: 44927 | I12: =IFERROR(YEAR(H12), "N/A") -> 2023 | J12: {=IFERROR(TEXT(H12, "[$-en-US]mmm"), _xleta.N/A)} -> Jan | K12: =IFERROR(DAY(H12), "N/A") -> 1 | L12: =IFERROR(TEXT(K12, "[$-en-US]dddd"), "N/A") -> Sunday | M12: =IF(AND(H12="Error",F12="Error"), "No","Yes") -> Yes
A13: Coffee | B13: 4 | C13: 2 | D13: 8 | E13: {=_xlfn.IFS(D13<=5, "$1-5", D13<=10, "$6-10",D13<=15,"$11-15", D13<=20, "$16-20", D13>20, "$20+")} -> $6-10 | F13: Digital Wallet | G13: In-store | H13: 44927 | I13: =IFERROR(YEAR(H13), "N/A") -> 2023 | J13: {=IFERROR(TEXT(H13, "[$-en-US]mmm"), _xleta.N/A)} -> Jan | K13: =IFERROR(DAY(H13), "N/A") -> 1 | L13: =IFERROR(TEXT(K13, "[$-en-US]dddd"), "N/A") -> Sunday | M13: =IF(AND(H13="Error",F13="Error"), "No","Yes") -> Yes
A14: Coffee | B14: =$D14/$C14 -> 1 | C14: 2 | D14: 2 | E14: {=_xlfn.IFS(D14<=5, "$1-5", D14<=10, "$6-10",D14<=15,"$11-15", D14<=20, "$16-20", D14>20, "$20+")} -> $1-5 | F14: Credit Card | G14: Unspecified | H14: 44927 | I14: =IFERROR(YEAR(H14), "N/A") -> 2023 | J14: {=IFERROR(TEXT(H14, "[$-en-US]mmm"), _xleta.N/A)} -> Jan | K14: =IFERROR(DAY(H14), "N/A") -> 1 | L14: =IFERROR(TEXT(K14, "[$-en-US]dddd"), "N/A") -> Sunday | M14: =IF(AND(H14="Error",F14="Error"), "No","Yes") -> Yes
A15: Coffee | B15: 2 | C15: 2 | D15: 4 | E15: {=_xlfn.IFS(D15<=5, "$1-5", D15<=10, "$6-10",D15<=15,"$11-15", D15<=20, "$16-20", D15>20, "$20+")} -> $1-5 | F15: Unspecified | G15: Unspecified | H15: 44927 | I15: =IFERROR(YEAR(H15), "N/A") -> 2023 | J15: {=IFERROR(TEXT(H15, "[$-en-US]mmm"), _xleta.N/A)} -> Jan | K15: =IFERROR(DAY(H15), "N/A") -> 1 | L15: =IFERROR(TEXT(K15, "[$-en-US]dddd"), "N/A") -> Sunday | M15: =IF(AND(H15="Error",F15="Error"), "No","Yes") -> Yes
A16: Cookie | B16: 4 | C16: 1 | D16: 4 | E16: {=_xlfn.IFS(D16<=5, "$1-5", D16<=10, "$6-10",D16<=15,"$11-15", D16<=20, "$16-20", D16>20, "$20+")} -> $1-5 | F16: Credit Card | G16: Error | H16: 44927 | I16: =IFERROR(YEAR(H16), "N/A") -> 2023 | J16: {=IFERROR(TEXT(H16, "[$-en-US]mmm"), _xleta.N/A)} -> Jan | K16: =IFERROR(DAY(H16), "N/A") -> 1 | L16: =IFERROR(TEXT(K16, "[$-en-US]dddd"), "N/A") -> Sunday | M16: =IF(AND(H16="Error",F16="Error"), "No","Yes") -> Yes
A17: Tea | B17: 5 | C17: 1.5 | D17: =$B17*$C17 -> 7.5 | E17: {=_xlfn.IFS(D17<=5, "$1-5", D17<=10, "$6-10",D17<=15,"$11-15", D17<=20, "$16-20", D17>20, "$20+")} -> $6-10 | F17: Unspecified | G17: Takeaway | H17: 44927 | I17: =IFERROR(YEAR(H17), "N/A") -> 2023 | J17: {=IFERROR(TEXT(H17, "[$-en-US]mmm"), _xleta.N/A)} -> Jan | K17: =IFERROR(DAY(H17), "N/A") -> 1 | L17: =IFERROR(TEXT(K17, "[$-en-US]dddd"), "N/A") -> Sunday | M17: =IF(AND(H17="Error",F17="Error"), "No","Yes") -> Yes
A18: Juice | B18: 1 | C18: 3 | D18: 3 | E18: {=_xlfn.IFS(D18<=5, "$1-5", D18<=10, "$6-10",D18<=15,"$11-15", D18<=20, "$16-20", D18>20, "$20+")} -> $1-5 | F18: Digital Wallet | G18: Takeaway | H18: 44927 | I18: =IFERROR(YEAR(H18), "N/A") -> 2023 | J18: {=IFERROR(TEXT(H18, "[$-en-US]mmm"), _xleta.N/A)} -> Jan | K18: =IFERROR(DAY(H18), "N/A") -> 1 | L18: =IFERROR(TEXT(K18, "[$-en-US]dddd"), "N/A") -> Sunday | M18: =IF(AND(H18="Error",F18="Error"), "No","Yes") -> Yes
A19: Coffee | B19: 2 | C19: 2 | D19: 4 | E19: {=_xlfn.IFS(D19<=5, "$1-5", D19<=10, "$6-10",D19<=15,"$11-15", D19<=20, "$16-20", D19>20, "$20+")} -> $1-5 | F19: Cash | G19: In-store | H19: 44927 | I19: =IFERROR(YEAR(H19), "N/A") -> 2023 | J19: {=IFERROR(TEXT(H19, "[$-en-US]mmm"), _xleta.N/A)} -> Jan | K19: =IFERROR(DAY(H19), "N/A") -> 1 | L19: =IFERROR(TEXT(K19, "[$-en-US]dddd"), "N/A") -> Sunday | M19: =IF(AND(H19="Error",F19="Error"), "No","Yes") -> Yes
A20: Smoothie | B20: 2 | C20: 4 | D20: 8 | E20: {=_xlfn.IFS(D20<=5, "$1-5", D20<=10, "$6-10",D20<=15,"$11-15", D20<=20, "$16-20", D20>20, "$20+")} -> $6-10 | F20: Digital Wallet | G20: In-store | H20: 44927 | I20: =IFERROR(YEAR(H20), "N/A") -> 2023 | J20: {=IFERROR(TEXT(H20, "[$-en-US]mmm"), _xleta.N/A)} -> Jan | K20: =IFERROR(DAY(H20), "N/A") -> 1 | L20: =IFERROR(TEXT(K20, "[$-en-US]dddd"), "N/A") -> Sunday | M20: =IF(AND(H20="Error",F20="Error"), "No","Yes") -> Yes
A21: Cake | B21: 3 | C21: 3 | D21: 9 | E21: {=_xlfn.IFS(D21<=5, "$1-5", D21<=10, "$6-10",D21<=15,"$11-15", D21<=20, "$16-20", D21>20, "$20+")} -> $6-10 | F21: Digital Wallet | G21: Takeaway | H21: 44927 | I21: =IFERROR(YEAR(H21), "N/A") -> 2023 | J21: {=IFERROR(TEXT(H21, "[$-en-US]mmm"), _xleta.N/A)} -> Jan | K21: =IFERROR(DAY(H21), "N/A") -> 1 | L21: =IFERROR(TEXT(K21, "[$-en-US]dddd"), "N/A") -> Sunday | M21: =IF(AND(H21="Error",F21="Error"), "No","Yes") -> Yes
A22: Sandwich | B22: 5 | C22: 4 | D22: 20 | E22: {=_xlfn.IFS(D22<=5, "$1-5", D22<=10, "$6-10",D22<=15,"$11-15", D22<=20, "$16-20", D22>20, "$20+")} -> $16-20 | F22: Credit Card | G22: In-store | H22: 44928 | I22: =IFERROR(YEAR(H22), "N/A") -> 2023 | J22: {=IFERROR(TEXT(H22, "[$-en-US]mmm"), _xleta.N/A)} -> Jan | K22: =IFERROR(DAY(H22), "N/A") -> 2 | L22: =IFERROR(TEXT(K22, "[$-en-US]dddd"), "N/A") -> Monday | M22: =IF(AND(H22="Error",F22="Error"), "No","Yes") -> Yes
A23: Cookie | B23: 4 | C23: 1 | D23: 4 | E23: {=_xlfn.IFS(D23<=5, "$1-5", D23<=10, "$6-10",D23<=15,"$11-15", D23<=20, "$16-20", D23>20, "$20+")} -> $1-5 | F23: Digital Wallet | G23: In-store | H23: 44928 | I23: =IFERROR(YEAR(H23), "N/A") -> 2023 | J23: {=IFERROR(TEXT(H23, "[$-en-US]mmm"), _xleta.N/A)} -> Jan | K23: =IFERROR(DAY(H23), "N/A") -> 2 | L23: =IFERROR(TEXT(K23, "[$-en-US]dddd"), "N/A") -> Monday | M23: =IF(AND(H23="Error",F23="Error"), "No","Yes") -> Yes
A24: Unspecified | B24: 5 | C24: 4 | D24: 20 | E24: {=_xlfn.IFS(D24<=5, "$1-5", D24<=10, "$6-10",D24<=15,"$11-15", D24<=20, "$16-20", D24>20, "$20+")} -> $16-20 | F24: Credit Card | G24: Unspecified | H24: 44928 | I24: =IFERROR(YEAR(H24), "N/A") -> 2023 | J24: {=IFERROR(TEXT(H24, "[$-en-US]mmm"), _xleta.N/A)} -> Jan | K24: =IFERROR(DAY(H24), "N/A") -> 2 | L24: =IFERROR(TEXT(K24, "[$-en-US]dddd"), "N/A") -> Monday | M24: =IF(AND(H24="Error",F24="Error"), "No","Yes") -> Yes
A25: Smoothie | B25: 1 | C25: 4 | D25: 4 | E25: {=_xlfn.IFS(D25<=5, "$1-5", D25<=10, "$6-10",D25<=15,"$11-15", D25<=20, "$16-20", D25>20, "$20+")} -> $1-5 | F25: Unspecified | G25: Takeaway | H25: 44928 | I25: =IFERROR(YEAR(H25), "N/A") -> 2023 | J25: {=IFERROR(TEXT(H25, "[$-en-US]mmm"), _xleta.N/A)} -> Jan | K25: =IFERROR(DAY(H25), "N/A") -> 2 | L25: =IFERROR(TEXT(K25, "[$-en-US]dddd"), "N/A") -> Monday | M25: =IF(AND(H25="Error",F25="Error"), "No","Yes") -> Yes
A26: Salad | B26: 2 | C26: 5 | D26: 10 | E26: {=_xlfn.IFS(D26<=5, "$1-5", D26<=10, "$6-10",D26<=15,"$11-15", D26<=20, "$16-20", D26>20, "$20+")} -> $6-10 | F26: Unspecified | G26: Unspecified | H26: 44928 | I26: =IFERROR(YEAR(H26), "N/A") -> 2023 | J26: {=IFERROR(TEXT(H26, "[$-en-US]mmm"), _xleta.N/A)} -> Jan | K26: =IFERROR(DAY(H26), "N/A") -> 2 | L26: =IFERROR(TEXT(K26, "[$-en-US]dddd"), "N/A") -> Monday | M26: =IF(AND(H26="Error",F26="Error"), "No","Yes") -> Yes
A27: Sandwich | B27: 5 | C27: 4 | D27: =$B27*$C27 -> 20 | E27: {=_xlfn.IFS(D27<=5, "$1-5", D27<=10, "$6-10",D27<=15,"$11-15", D27<=20, "$16-20", D27>20, "$20+")} -> $16-20 | F27: Credit Card | G27: In-store | H27: 44928 | I27: =IFERROR(YEAR(H27), "N/A") -> 2023 | J27: {=IFERROR(TEXT(H27, "[$-en-US]mmm"), _xleta.N/A)} -> Jan | K27: =IFERROR(DAY(H27), "N/A") -> 2 | L27: =IFERROR(TEXT(K27, "[$-en-US]dddd"), "N/A") -> Monday | M27: =IF(AND(H27="Error",F27="Error"), "No","Yes") -> Yes
A28: Smoothie | B28: =$D28/$C28 -> 5 | C28: 4 | D28: 20 | E28: {=_xlfn.IFS(D28<=5, "$1-5", D28<=10, "$6-10",D28<=15,"$11-15", D28<=20, "$16-20", D28>20, "$20+")} -> $16-20 | F28: Cash | G28: Unspecified | H28: 44928 | I28: =IFERROR(YEAR(H28), "N/A") -> 2023 | J28: {=IFERROR(TEXT(H28, "[$-en-US]mmm"), _xleta.N/A)} -> Jan | K28: =IFERROR(DAY(H28), "N/A") -> 2 | L28: =IFERROR(TEXT(K28, "[$-en-US]dddd"), "N/A") -> Monday | M28: =IF(AND(H28="Error",F28="Error"), "No","Yes") -> Yes
A29: Sandwich | B29: 2 | C29: 4 | D29: =$B29*$C29 -> 8 | E29: {=_xlfn.IFS(D29<=5, "$1-5", D29<=10, "$6-10",D29<=15,"$11-15", D29<=20, "$16-20", D29>20, "$20+")} -> $6-10 | F29: Credit Card | G29: In-store | H29: 44928 | I29: =IFERROR(YEAR(H29), "N/A") -> 2023 | J29: {=IFERROR(TEXT(H29, "[$-en-US]mmm"), _xleta.N/A)} -> Jan | K29: =IFERROR(DAY(H29), "N/A") -> 2 | L29: =IFERROR(TEXT(K29, "[$-en-US]dddd"), "N/A") -> Monday | M29: =IF(AND(H29="Error",F29="Error"), "No","Yes") -> Yes
A30: Cookie | B30: 5 | C30: 1 | D30: 5 | E30: {=_xlfn.IFS(D30<=5, "$1-5", D30<=10, "$6-10",D30<=15,"$11-15", D30<=20, "$16-20", D30>20, "$20+")} -> $1-5 | F30: Credit Card | G30: Unspecified | H30: 44928 | I30: =IFERROR(YEAR(H30), "N/A") -> 2023 | J30: {=IFERROR(TEXT(H30, "[$-en-US]mmm"), _xleta.N/A)} -> Jan | K30: =IFERROR(DAY(H30), "N/A") -> 2 | L30: =IFERROR(TEXT(K30, "[$-en-US]dddd"), "N/A") -> Monday | M30: =IF(AND(H30="Error",F30="Error"), "No","Yes") -> Yes
A31: Cake | B31: 2 | C31: 3 | D31: 6 | E31: {=_xlfn.IFS(D31<=5, "$1-5", D31<=10, "$6-10",D31<=15,"$11-15", D31<=20, "$16-20", D31>20, "$20+")} -> $6-10 | F31: Cash | G31: Takeaway | H31: 44928 | I31: =IFERROR(YEAR(H31), "N/A") -> 2023 | J31: {=IFERROR(TEXT(H31, "[$-en-US]mmm"), _xleta.N/A)} -> Jan | K31: =IFERROR(DAY(H31), "N/A") -> 2 | L31: =IFERROR(TEXT(K31, "[$-en-US]dddd"), "N/A") -> Monday | M31: =IF(AND(H31="Error",F31="Error"), "No","Yes") -> Yes
A32: Smoothie | B32: 2 | C32: 4 | D32: 8 | E32: {=_xlfn.IFS(D32<=5, "$1-5", D32<=10, "$6-10",D32<=15,"$11-15", D32<=20, "$16-20", D32>20, "$20+")} -> $6-10 | F32: Unspecified | G32: In-store | H32: 44928 | I32: =IFERROR(YEAR(H32), "N/A") -> 2023 | J32: {=IFERROR(TEXT(H32, "[$-en-US]mmm"), _xleta.N/A)} -> Jan | K32: =IFERROR(DAY(H32), "N/A") -> 2 | L32: =IFERROR(TEXT(K32, "[$-en-US]dddd"), "N/A") -> Monday | M32: =IF(AND(H32="Error",F32="Error"), "No","Yes") -> Yes
A33: =_xlfn.XLOOKUP(C33,'Item Price'!$B:$B,'Item Price'!$A:$A,"notfound") -> Tea | B33: 2 | C33: 1.5 | D33: 3 | E33: {=_xlfn.IFS(D33<=5, "$1-5", D33<=10, "$6-10",D33<=15,"$11-15", D33<=20, "$16-20", D33>20, "$20+")} -> $1-5 | F33: Credit Card | G33: Takeaway | H33: 44928 | I33: =IFERROR(YEAR(H33), "N/A") -> 2023 | J33: {=IFERROR(TEXT(H33, "[$-en-US]mmm"), _xleta.N/A)} -> Jan | K33: =IFERROR(DAY(H33), "N/A") -> 2 | L33: =IFERROR(TEXT(K33, "[$-en-US]dddd"), "N/A") -> Monday | M33: =IF(AND(H33="Error",F33="Error"), "No","Yes") -> Yes
A34: Cookie | B34: =$D34/$C34 -> 4 | C34: 1 | D34: 4 | E34: {=_xlfn.IFS(D34<=5, "$1-5", D34<=10, "$6-10",D34<=15,"$11-15", D34<=20, "$16-20", D34>20, "$20+")} -> $1-5 | F34: Unspecified | G34: Takeaway | H34: 44928 | I34: =IFERROR(YEAR(H34), "N/A") -> 2023 | J34: {=IFERROR(TEXT(H34, "[$-en-US]mmm"), _xleta.N/A)} -> Jan | K34: =IFERROR(DAY(H34), "N/A") -> 2 | L34: =IFERROR(TEXT(K34, "[$-en-US]dddd"), "N/A") -> Monday | M34: =IF(AND(H34="Error",F34="Error"), "No","Yes") -> Yes
A35: Coffee | B35: 3 | C35: 2 | D35: 6 | E35: {=_xlfn.IFS(D35<=5, "$1-5", D35<=10, "$6-10",D35<=15,"$11-15", D35<=20, "$16-20", D35>20, "$20+")} -> $6-10 | F35: Unspecified | G35: Unspecified | H35: 44928 | I35: =IFERROR(YEAR(H35), "N/A") -> 2023 | J35: {=IFERROR(TEXT(H35, "[$-en-US]mmm"), _xleta.N/A)} -> Jan | K35: =IFERROR(DAY(H35), "N/A") -> 2 | L35: =IFERROR(TEXT(K35, "[$-en-US]dddd"), "N/A") -> Monday | M35: =IF(AND(H35="Error",F35="Error"), "No","Yes") -> Yes
A36: Cake | B36: 4 | C36: 3 | D36: 12 | E36: {=_xlfn.IFS(D36<=5, "$1-5", D36<=10, "$6-10",D36<=15,"$11-15", D36<=20, "$16-20", D36>20, "$20+")} -> $11-15 | F36: Cash | G36: Error | H36: 44928 | I36: =IFERROR(YEAR(H36), "N/A") -> 2023 | J36: {=IFERROR(TEXT(H36, "[$-en-US]mmm"), _xleta.N/A)} -> Jan | K36: =IFERROR(DAY(H36), "N/A") -> 2 | L36: =IFERROR(TEXT(K36, "[$-en-US]dddd"), "N/A") -> Monday | M36: =IF(AND(H36="Error",F36="Error"), "No","Yes") -> Yes
A37: Sandwich | B37: 4 | C37: 4 | D37: 16 | E37: {=_xlfn.IFS(D37<=5, "$1-5", D37<=10, "$6-10",D37<=15,"$11-15", D37<=20, "$16-20", D37>20, "$20+")} -> $16-20 | F37: Cash | G37: Takeaway | H37: 44928 | I37: =IFERROR(YEAR(H37), "N/A") -> 2023 | J37: {=IFERROR(TEXT(H37, "[$-en-US]mmm"), _xleta.N/A)} -> Jan | K37: =IFERROR(DAY(H37), "N/A") -> 2 | L37: =IFERROR(TEXT(K37, "[$-en-US]dddd"), "N/A") -> Monday | M37: =IF(AND(H37="Error",F37="Error"), "No","Yes") -> Yes
A38: Salad | B38: 2 | C38: 5 | D38: 10 | E38: {=_xlfn.IFS(D38<=5, "$1-5", D38<=10, "$6-10",D38<=15,"$11-15", D38<=20, "$16-20", D38>20, "$20+")} -> $6-10 | F38: Cash | G38: Takeaway | H38: 44928 | I38: =IFERROR(YEAR(H38), "N/A") -> 2023 | J38: {=IFERROR(TEXT(H38, "[$-en-US]mmm"), _xleta.N/A)} -> Jan | K38: =IFERROR(DAY(H38), "N/A") -> 2 | L38: =IFERROR(TEXT(K38, "[$-en-US]dddd"), "N/A") -> Monday | M38: =IF(AND(H38="Error",F38="Error"), "No","Yes") -> Yes
A39: Cake | B39: 1 | C39: 3 | D39: 3 | E39: {=_xlfn.IFS(D39<=5, "$1-5", D39<=10, "$6-10",D39<=15,"$11-15", D39<=20, "$16-20", D39>20, "$20+")} -> $1-5 | F39: Credit Card | G39: Takeaway | H39: 44928 | I39: =IFERROR(YEAR(H39), "N/A") -> 2023 | J39: {=IFERROR(TEXT(H39, "[$-en-US]mmm"), _xleta.N/A)} -> Jan | K39: =IFERROR(DAY(H39), "N/A") -> 2 | L39: =IFERROR(TEXT(K39, "[$-en-US]dddd"), "N/A") -> Monday | M39: =IF(AND(H39="Error",F39="Error"), "No","Yes") -> Yes
A40: Tea | B40: 1 | C40: 1.5 | D40: 1.5 | E40: {=_xlfn.IFS(D40<=5, "$1-5", D40<=10, "$6-10",D40<=15,"$11-15", D40<=20, "$16-20", D40>20, "$20+")} -> $1-5 | F40: Unspecified | G40: Unspecified | H40: 44928 | I40: =IFERROR(YEAR(H40), "N/A") -> 2023 | J40: {=IFERROR(TEXT(H40, "[$-en-US]mmm"), _xleta.N/A)} -> Jan | K40: =IFERROR(DAY(H40), "N/A") -> 2 | L40: =IFERROR(TEXT(K40, "[$-en-US]dddd"), "N/A") -> Monday | M40: =IF(AND(H40="Error",F40="Error"), "No","Yes") -> Yes
A41: Tea | B41: 1 | C41: 1.5 | D41: 1.5 | E41: {=_xlfn.IFS(D41<=5, "$1-5", D41<=10, "$6-10",D41<=15,"$11-15", D41<=20, "$16-20", D41>20, "$20+")} -> $1-5 | F41: Unspecified | G41: In-store | H41: 44928 | I41: =IFERROR(YEAR(H41), "N/A") -> 2023 | J41: {=IFERROR(TEXT(H41, "[$-en-US]mmm"), _xleta.N/A)} -> Jan | K41: =IFERROR(DAY(H41), "N/A") -> 2 | L41: =IFERROR(TEXT(K41, "[$-en-US]dddd"), "N/A") -> Monday | M41: =IF(AND(H41="Error",F41="Error"), "No","Yes") -> Yes
A42: Tea | B42: 5 | C42: 1.5 | D42: 7.5 | E42: {=_xlfn.IFS(D42<=5, "$1-5", D42<=10, "$6-10",D42<=15,"$11-15", D42<=20, "$16-20", D42>20, "$20+")} -> $6-10 | F42: Unspecified | G42: Unspecified | H42: 44928 | I42: =IFERROR(YEAR(H42), "N/A") -> 2023 | J42: {=IFERROR(TEXT(H42, "[$-en-US]mmm"), _xleta.N/A)} -> Jan | K42: =IFERROR(DAY(H42), "N/A") -> 2 | L42: =IFERROR(TEXT(K42, "[$-en-US]dddd"), "N/A") -> Monday | M42: =IF(AND(H42="Error",F42="Error"), "No","Yes") -> Yes
A43: =_xlfn.XLOOKUP(C43,'Item Price'!B:B,'Item Price'!A:A) -> Tea | B43: 2 | C43: 1.5 | D43: 3 | E43: {=_xlfn.IFS(D43<=5, "$1-5", D43<=10, "$6-10",D43<=15,"$11-15", D43<=20, "$16-20", D43>20, "$20+")} -> $1-5 | F43: Cash | G43: In-store | H43: 44929 | I43: =IFERROR(YEAR(H43), "N/A") -> 2023 | J43: {=IFERROR(TEXT(H43, "[$-en-US]mmm"), _xleta.N/A)} -> Jan | K43: =IFERROR(DAY(H43), "N/A") -> 3 | L43: =IFERROR(TEXT(K43, "[$-en-US]dddd"), "N/A") -> Tuesday | M43: =IF(AND(H43="Error",F43="Error"), "No","Yes") -> Yes
A44: Cake | B44: 4 | C44: 3 | D44: 12 | E44: {=_xlfn.IFS(D44<=5, "$1-5", D44<=10, "$6-10",D44<=15,"$11-15", D44<=20, "$16-20", D44>20, "$20+")} -> $11-15 | F44: Credit Card | G44: Takeaway | H44: 44929 | I44: =IFERROR(YEAR(H44), "N/A") -> 2023 | J44: {=IFERROR(TEXT(H44, "[$-en-US]mmm"), _xleta.N/A)} -> Jan | K44: =IFERROR(DAY(H44), "N/A") -> 3 | L44: =IFERROR(TEXT(K44, "[$-en-US]dddd"), "N/A") -> Tuesday | M44: =IF(AND(H44="Error",F44="Error"), "No","Yes") -> Yes
A45: Salad | B45: 5 | C45: 5 | D45: 25 | E45: {=_xlfn.IFS(D45<=5, "$1-5", D45<=10, "$6-10",D45<=15,"$11-15", D45<=20, "$16-20", D45>20, "$20+")} -> $20+ | F45: Unspecified | G45: Takeaway | H45: 44929 | I45: =IFERROR(YEAR(H45), "N/A") -> 2023 | J45: {=IFERROR(TEXT(H45, "[$-en-US]mmm"), _xleta.N/A)} -> Jan | K45: =IFERROR(DAY(H45), "N/A") -> 3 | L45: =IFERROR(TEXT(K45, "[$-en-US]dddd"), "N/A") -> Tuesday | M45: =IF(AND(H45="Error",F45="Error"), "No","Yes") -> Yes
A46: Sandwich | B46: 4 | C46: 4 | D46: 16 | E46: {=_xlfn.IFS(D46<=5, "$1-5", D46<=10, "$6-10",D46<=15,"$11-15", D46<=20, "$16-20", D46>20, "$20+")} -> $16-20 | F46: Credit Card | G46: In-store | H46: 44929 | I46: =IFERROR(YEAR(H46), "N/A") -> 2023 | J46: {=IFERROR(TEXT(H46, "[$-en-US]mmm"), _xleta.N/A)} -> Jan | K46: =IFERROR(DAY(H46), "N/A") -> 3 | L46: =IFERROR(TEXT(K46, "[$-en-US]dddd"), "N/A") -> Tuesday | M46: =IF(AND(H46="Error",F46="Error"), "No","Yes") -> Yes
A47: Juice | B47: 4 | C47: 3 | D47: =$B47*$C47 -> 12 | E47: {=_xlfn.IFS(D47<=5, "$1-5", D47<=10, "$6-10",D47<=15,"$11-15", D47<=20, "$16-20", D47>20, "$20+")} -> $11-15 | F47: Digital Wallet | G47: Takeaway | H47: 44929 | I47: =IFERROR(YEAR(H47), "N/A") -> 2023 | J47: {=IFERROR(TEXT(H47, "[$-en-US]mmm"), _xleta.N/A)} -> Jan | K47: =IFERROR(DAY(H47), "N/A") -> 3 | L47: =IFERROR(TEXT(K47, "[$-en-US]dddd"), "N/A") -> Tuesday | M47: =IF(AND(H47="Error",F47="Error"), "No","Yes") -> Yes
A48: Cookie | B48: 2 | C48: 1 | D48: 2 | E48: {=_xlfn.IFS(D48<=5, "$1-5", D48<=10, "$6-10",D48<=15,"$11-15", D48<=20, "$16-20", D48>20, "$20+")} -> $1-5 | F48: Credit Card | G48: Takeaway | H48: 44929 | I48: =IFERROR(YEAR(H48), "N/A") -> 2023 | J48: {=IFERROR(TEXT(H48, "[$-en-US]mmm"), _xleta.N/A)} -> Jan | K48: =IFERROR(DAY(H48), "N/A") -> 3 | L48: =IFERROR(TEXT(K48, "[$-en-US]dddd"), "N/A") -> Tuesday | M48: =IF(AND(H48="Error",F48="Error"), "No","Yes") -> Yes
A49: Coffee | B49: 3 | C49: 2 | D49: 6 | E49: {=_xlfn.IFS(D49<=5, "$1-5", D49<=10, "$6-10",D49<=15,"$11-15", D49<=20, "$16-20", D49>20, "$20+")} -> $6-10 | F49: Digital Wallet | G49: Takeaway | H49: 44929 | I49: =IFERROR(YEAR(H49), "N/A") -> 2023 | J49: {=IFERROR(TEXT(H49, "[$-en-US]mmm"), _xleta.N/A)} -> Jan | K49: =IFERROR(DAY(H49), "N/A") -> 3 | L49: =IFERROR(TEXT(K49, "[$-en-US]dddd"), "N/A") -> Tuesday | M49: =IF(AND(H49="Error",F49="Error"), "No","Yes") -> Yes
A50: Cake | B50: 5 | C50: 3 | D50: 15 | E50: {=_xlfn.IFS(D50<=5, "$1-5", D50<=10, "$6-10",D50<=15,"$11-15", D50<=20, "$16-20", D50>20, "$20+")} -> $11-15 | F50: Cash | G50: Unspecified | H50: 44929 | I50: =IFERROR(YEAR(H50), "N/A") -> 2023 | J50: {=IFERROR(TEXT(H50, "[$-en-US]mmm"), _xleta.N/A)} -> Jan | K50: =IFERROR(DAY(H50), "N/A") -> 3 | L50: =IFERROR(TEXT(K50, "[$-en-US]dddd"), "N/A") -> Tuesday | M50: =IF(AND(H50="Error",F50="Error"), "No","Yes") -> Yes
A51: Juice | B51: 4 | C51: 3 | D51: 12 | E51: {=_xlfn.IFS(D51<=5, "$1-5", D51<=10, "$6-10",D51<=15,"$11-15", D51<=20, "$16-20", D51>20, "$20+")} -> $11-15 | F51: Unspecified | G51: Takeaway | H51: 44929 | I51: =IFERROR(YEAR(H51), "N/A") -> 2023 | J51: {=IFERROR(TEXT(H51, "[$-en-US]mmm"), _xleta.N/A)} -> Jan | K51: =IFERROR(DAY(H51), "N/A") -> 3 | L51: =IFERROR(TEXT(K51, "[$-en-US]dddd"), "N/A") -> Tuesday | M51: =IF(AND(H51="Error",F51="Error"), "No","Yes") -> Yes
A52: Cookie | B52: 1 | C52: 1 | D52: 1 | E52: {=_xlfn.IFS(D52<=5, "$1-5", D52<=10, "$6-10",D52<=15,"$11-15", D52<=20, "$16-20", D52>20, "$20+")} -> $1-5 | F52: Unspecified | G52: Takeaway | H52: 44929 | I52: =IFERROR(YEAR(H52), "N/A") -> 2023 | J52: {=IFERROR(TEXT(H52, "[$-en-US]mmm"), _xleta.N/A)} -> Jan | K52: =IFERROR(DAY(H52), "N/A") -> 3 | L52: =IFERROR(TEXT(K52, "[$-en-US]dddd"), "N/A") -> Tuesday | M52: =IF(AND(H52="Error",F52="Error"), "No","Yes") -> Yes
A53: Sandwich | B53: 2 | C53: 4 | D53: 8 | E53: {=_xlfn.IFS(D53<=5, "$1-5", D53<=10, "$6-10",D53<=15,"$11-15", D53<=20, "$16-20", D53>20, "$20+")} -> $6-10 | F53: Credit Card | G53: Takeaway | H53: 44929 | I53: =IFERROR(YEAR(H53), "N/A") -> 2023 | J53: {=IFERROR(TEXT(H53, "[$-en-US]mmm"), _xleta.N/A)} -> Jan | K53: =IFERROR(DAY(H53), "N/A") -> 3 | L53: =IFERROR(TEXT(K53, "[$-en-US]dddd"), "N/A") -> Tuesday | M53: =IF(AND(H53="Error",F53="Error"), "No","Yes") -> Yes
A54: Juice | B54: 1 | C54: 3 | D54: 3 | E54: {=_xlfn.IFS(D54<=5, "$1-5", D54<=10, "$6-10",D54<=15,"$11-15", D54<=20, "$16-20", D54>20, "$20+")} -> $1-5 | F54: Unspecified | G54: Takeaway | H54: 44929 | I54: =IFERROR(YEAR(H54), "N/A") -> 2023 | J54: {=IFERROR(TEXT(H54, "[$-en-US]mmm"), _xleta.N/A)} -> Jan | K54: =IFERROR(DAY(H54), "N/A") -> 3 | L54: =IFERROR(TEXT(K54, "[$-en-US]dddd"), "N/A") -> Tuesday | M54: =IF(AND(H54="Error",F54="Error"), "No","Yes") -> Yes
A55: Cookie | B55: 1 | C55: 1 | D55: 1 | E55: {=_xlfn.IFS(D55<=5, "$1-5", D55<=10, "$6-10",D55<=15,"$11-15", D55<=20, "$16-20", D55>20, "$20+")} -> $1-5 | F55: Unspecified | G55: Unspecified | H55: 44929 | I55: =IFERROR(YEAR(H55), "N/A") -> 2023 | J55: {=IFERROR(TEXT(H55, "[$-en-US]mmm"), _xleta.N/A)} -> Jan | K55: =IFERROR(DAY(H55), "N/A") -> 3 | L55: =IFERROR(TEXT(K55, "[$-en-US]dddd"), "N/A") -> Tuesday | M55: =IF(AND(H55="Error",F55="Error"), "No","Yes") -> Yes
A56: Salad | B56: 3 | C56: 5 | D56: =$B56*$C56 -> 15 | E56: {=_xlfn.IFS(D56<=5, "$1-5", D56<=10, "$6-10",D56<=15,"$11-15", D56<=20, "$16-20", D56>20, "$20+")} -> $11-15 | F56: Cash | G56: Error | H56: 44929 | I56: =IFERROR(YEAR(H56), "N/A") -> 2023 | J56: {=IFERROR(TEXT(H56, "[$-en-US]mmm"), _xleta.N/A)} -> Jan | K56: =IFERROR(DAY(H56), "N/A") -> 3 | L56: =IFERROR(TEXT(K56, "[$-en-US]dddd"), "N/A") -> Tuesday | M56: =IF(AND(H56="Error",F56="Error"), "No","Yes") -> Yes
A57: Smoothie | B57: 3 | C57: 4 | D57: =$B57*$C57 -> 12 | E57: {=_xlfn.IFS(D57<=5, "$1-5", D57<=10, "$6-10",D57<=15,"$11-15", D57<=20, "$16-20", D57>20, "$20+")} -> $11-15 | F57: Unspecified | G57: Unspecified | H57: 44929 | I57: =IFERROR(YEAR(H57), "N/A") -> 2023 | J57: {=IFERROR(TEXT(H57, "[$-en-US]mmm"), _xleta.N/A)} -> Jan | K57: =IFERROR(DAY(H57), "N/A") -> 3 | L57: =IFERROR(TEXT(K57, "[$-en-US]dddd"), "N/A") -> Tuesday | M57: =IF(AND(H57="Error",F57="Error"), "No","Yes") -> Yes
A58: Smoothie | B58: 0 | C58: 4 | D58: 0 | E58: {=_xlfn.IFS(D58<=5, "$1-5", D58<=10, "$6-10",D58<=15,"$11-15", D58<=20, "$16-20", D58>20, "$20+")} -> $1-5 | F58: Cash | G58: In-store | H58: 44929 | I58: =IFERROR(YEAR(H58), "N/A") -> 2023 | J58: {=IFERROR(TEXT(H58, "[$-en-US]mmm"), _xleta.N/A)} -> Jan | K58: =IFERROR(DAY(H58), "N/A") -> 3 | L58: =IFERROR(TEXT(K58, "[$-en-US]dddd"), "N/A") -> Tuesday | M58: =IF(AND(H58="Error",F58="Error"), "No","Yes") -> Yes
A59: Unspecified | B59: =$D59/$C59 -> 3 | C59: 4 | D59: 12 | E59: {=_xlfn.IFS(D59<=5, "$1-5", D59<=10, "$6-10",D59<=15,"$11-15", D59<=20, "$16-20", D59>20, "$20+")} -> $11-15 | F59: Unspecified | G59: In-store | H59: 44929 | I59: =IFERROR(YEAR(H59), "N/A") -> 2023 | J59: {=IFERROR(TEXT(H59, "[$-en-US]mmm"), _xleta.N/A)} -> Jan | K59: =IFERROR(DAY(H59), "N/A") -> 3 | L59: =IFERROR(TEXT(K59, "[$-en-US]dddd"), "N/A") -> Tuesday | M59: =IF(AND(H59="Error",F59="Error"), "No","Yes") -> Yes
A60: Juice | B60: 4 | C60: 3 | D60: 12 | E60: {=_xlfn.IFS(D60<=5, "$1-5", D60<=10, "$6-10",D60<=15,"$11-15", D60<=20, "$16-20", D60>20, "$20+")} -> $11-15 | F60: Cash | G60: Unspecified | H60: 44929 | I60: =IFERROR(YEAR(H60), "N/A") -> 2023 | J60: {=IFERROR(TEXT(H60, "[$-en-US]mmm"), _xleta.N/A)} -> Jan | K60: =IFERROR(DAY(H60), "N/A") -> 3 | L60: =IFERROR(TEXT(K60, "[$-en-US]dddd"), "N/A") -> Tuesday | M60: =IF(AND(H60="Error",F60="Error"), "No","Yes") -> Yes
A61: Cake | B61: 5 | C61: 3 | D61: =$B61*$C61 -> 15 | E61: {=_xlfn.IFS(D61<=5, "$1-5", D61<=10, "$6-10",D61<=15,"$11-15", D61<=20, "$16-20", D61>20, "$20+")} -> $11-15 | F61: Credit Card | G61: Takeaway | H61: 44929 | I61: =IFERROR(YEAR(H61), "N/A") -> 2023 | J61: {=IFERROR(TEXT(H61, "[$-en-US]mmm"), _xleta.N/A)} -> Jan | K61: =IFERROR(DAY(H61), "N/A") -> 3 | L61: =IFERROR(TEXT(K61, "[$-en-US]dddd"), "N/A") -> Tuesday | M61: =IF(AND(H61="Error",F61="Error"), "No","Yes") -> Yes
A62: Cake | B62: 2 | C62: 3 | D62: 6 | E62: {=_xlfn.IFS(D62<=5, "$1-5", D62<=10, "$6-10",D62<=15,"$11-15", D62<=20, "$16-20", D62>20, "$20+")} -> $6-10 | F62: Error | G62: In-store | H62: 44929 | I62: =IFERROR(YEAR(H62), "N/A") -> 2023 | J62: {=IFERROR(TEXT(H62, "[$-en-US]mmm"), _xleta.N/A)} -> Jan | K62: =IFERROR(DAY(H62), "N/A") -> 3 | L62: =IFERROR(TEXT(K62, "[$-en-US]dddd"), "N/A") -> Tuesday | M62: =IF(AND(H62="Error",F62="Error"), "No","Yes") -> Yes
A63: Cake | B63: 2 | C63: 3 | D63: 6 | E63: {=_xlfn.IFS(D63<=5, "$1-5", D63<=10, "$6-10",D63<=15,"$11-15", D63<=20, "$16-20", D63>20, "$20+")} -> $6-10 | F63: Unspecified | G63: Unspecified | H63: 44929 | I63: =IFERROR(YEAR(H63), "N/A") -> 2023 | J63: {=IFERROR(TEXT(H63, "[$-en-US]mmm"), _xleta.N/A)} -> Jan | K63: =IFERROR(DAY(H63), "N/A") -> 3 | L63: =IFERROR(TEXT(K63, "[$-en-US]dddd"), "N/A") -> Tuesday | M63: =IF(AND(H63="Error",F63="Error"), "No","Yes") -> Yes
A64: Unspecified | B64: 4 | C64: =$D64/$B64 -> 4 | D64: 16 | E64: {=_xlfn.IFS(D64<=5, "$1-5", D64<=10, "$6-10",D64<=15,"$11-15", D64<=20, "$16-20", D64>20, "$20+")} -> $16-20 | F64: Credit Card | G64: Takeaway | H64: 44930 | I64: =IFERROR(YEAR(H64), "N/A") -> 2023 | J64: {=IFERROR(TEXT(H64, "[$-en-US]mmm"), _xleta.N/A)} -> Jan | K64: =IFERROR(DAY(H64), "N/A") -> 4 | L64: =IFERROR(TEXT(K64, "[$-en-US]dddd"), "N/A") -> Wednesday | M64: =IF(AND(H64="Error",F64="Error"), "No","Yes") -> Yes
A65: Coffee | B65: 4 | C65: 2 | D65: 8 | E65: {=_xlfn.IFS(D65<=5, "$1-5", D65<=10, "$6-10",D65<=15,"$11-15", D65<=20, "$16-20", D65>20, "$20+")} -> $6-10 | F65: Unspecified | G65: In-store | H65: 44930 | I65: =IFERROR(YEAR(H65), "N/A") -> 2023 | J65: {=IFERROR(TEXT(H65, "[$-en-US]mmm"), _xleta.N/A)} -> Jan | K65: =IFERROR(DAY(H65), "N/A") -> 4 | L65: =IFERROR(TEXT(K65, "[$-en-US]dddd"), "N/A") -> Wednesday | M65: =IF(AND(H65="Error",F65="Error"), "No","Yes") -> Yes
A66: Tea | B66: 5 | C66: 1.5 | D66: 7.5 | E66: {=_xlfn.IFS(D66<=5, "$1-5", D66<=10, "$6-10",D66<=15,"$11-15", D66<=20, "$16-20", D66>20, "$20+")} -> $6-10 | F66: Credit Card | G66: Error | H66: 44930 | I66: =IFERROR(YEAR(H66), "N/A") -> 2023 | J66: {=IFERROR(TEXT(H66, "[$-en-US]mmm"), _xleta.N/A)} -> Jan | K66: =IFERROR(DAY(H66), "N/A") -> 4 | L66: =IFERROR(TEXT(K66, "[$-en-US]dddd"), "N/A") -> Wednesday | M66: =IF(AND(H66="Error",F66="Error"), "No","Yes") -> Yes
A67: Coffee | B67: 2 | C67: 2 | D67: 4 | E67: {=_xlfn.IFS(D67<=5, "$1-5", D67<=10, "$6-10",D67<=15,"$11-15", D67<=20, "$16-20", D67>20, "$20+")} -> $1-5 | F67: Credit Card | G67: Unspecified | H67: 44930 | I67: =IFERROR(YEAR(H67), "N/A") -> 2023 | J67: {=IFERROR(TEXT(H67, "[$-en-US]mmm"), _xleta.N/A)} -> Jan | K67: =IFERROR(DAY(H67), "N/A") -> 4 | L67: =IFERROR(TEXT(K67, "[$-en-US]dddd"), "N/A") -> Wednesday | M67: =IF(AND(H67="Error",F67="Error"), "No","Yes") -> Yes
A68: Salad | B68: 5 | C68: 5 | D68: 25 | E68: {=_xlfn.IFS(D68<=5, "$1-5", D68<=10, "$6-10",D68<=15,"$11-15", D68<=20, "$16-20", D68>20, "$20+")} -> $20+ | F68: Credit Card | G68: Unspecified | H68: 44930 | I68: =IFERROR(YEAR(H68), "N/A") -> 2023 | J68: {=IFERROR(TEXT(H68, "[$-en-US]mmm"), _xleta.N/A)} -> Jan | K68: =IFERROR(DAY(H68), "N/A") -> 4 | L68: =IFERROR(TEXT(K68, "[$-en-US]dddd"), "N/A") -> Wednesday | M68: =IF(AND(H68="Error",F68="Error"), "No","Yes") -> Yes
A69: =_xlfn.XLOOKUP(C69,'Item Price'!$B:$B,'Item Price'!$A:$A,"notfound") -> Tea | B69: 2 | C69: 1.5 | D69: 3 | E69: {=_xlfn.IFS(D69<=5, "$1-5", D69<=10, "$6-10",D69<=15,"$11-15", D69<=20, "$16-20", D69>20, "$20+")} -> $1-5 | F69: Credit Card | G69: Takeaway | H69: 44930 | I69: =IFERROR(YEAR(H69), "N/A") -> 2023 | J69: {=IFERROR(TEXT(H69, "[$-en-US]mmm"), _xleta.N/A)} -> Jan | K69: =IFERROR(DAY(H69), "N/A") -> 4 | L69: =IFERROR(TEXT(K69, "[$-en-US]dddd"), "N/A") -> Wednesday | M69: =IF(AND(H69="Error",F69="Error"), "No","Yes") -> Yes
A70: Coffee | B70: 3 | C70: 2 | D70: 6 | E70: {=_xlfn.IFS(D70<=5, "$1-5", D70<=10, "$6-10",D70<=15,"$11-15", D70<=20, "$16-20", D70>20, "$20+")} -> $6-10 | F70: Credit Card | G70: In-store | H70: 44930 | I70: =IFERROR(YEAR(H70), "N/A") -> 2023 | J70: {=IFERROR(TEXT(H70, "[$-en-US]mmm"), _xleta.N/A)} -> Jan | K70: =IFERROR(DAY(H70), "N/A") -> 4 | L70: =IFERROR(TEXT(K70, "[$-en-US]dddd"), "N/A") -> Wednesday | M70: =IF(AND(H70="Error",F70="Error"), "No","Yes") -> Yes
A71: Juice | B71: 2 | C71: =$D71/$B71 -> 3 | D71: 6 | E71: {=_xlfn.IFS(D71<=5, "$1-5", D71<=10, "$6-10",D71<=15,"$11-15", D71<=20, "$16-20", D71>20, "$20+")} -> $6-10 | F71: Credit Card | G71: Unspecified | H71: 44930 | I71: =IFERROR(YEAR(H71), "N/A") -> 2023 | J71: {=IFERROR(TEXT(H71, "[$-en-US]mmm"), _xleta.N/A)} -> Jan | K71: =IFERROR(DAY(H71), "N/A") -> 4 | L71: =IFERROR(TEXT(K71, "[$-en-US]dddd"), "N/A") -> Wednesday | M71: =IF(AND(H71="Error",F71="Error"), "No","Yes") -> Yes
A72: Smoothie | B72: 5 | C72: 4 | D72: 20 | E72: {=_xlfn.IFS(D72<=5, "$1-5", D72<=10, "$6-10",D72<=15,"$11-15", D72<=20, "$16-20", D72>20, "$20+")} -> $16-20 | F72: Credit Card | G72: Unspecified | H72: 44930 | I72: =IFERROR(YEAR(H72), "N/A") -> 2023 | J72: {=IFERROR(TEXT(H72, "[$-en-US]mmm"), _xleta.N/A)} -> Jan | K72: =IFERROR(DAY(H72), "N/A") -> 4 | L72: =IFERROR(TEXT(K72, "[$-en-US]dddd"), "N/A") -> Wednesday | M72: =IF(AND(H72="Error",F72="Error"), "No","Yes") -> Yes
A73: Sandwich | B73: 5 | C73: 4 | D73: 20 | E73: {=_xlfn.IFS(D73<=5, "$1-5", D73<=10, "$6-10",D73<=15,"$11-15", D73<=20, "$16-20", D73>20, "$20+")} -> $16-20 | F73: Digital Wallet | G73: Unspecified | H73: 44930 | I73: =IFERROR(YEAR(H73), "N/A") -> 2023 | J73: {=IFERROR(TEXT(H73, "[$-en-US]mmm"), _xleta.N/A)} -> Jan | K73: =IFERROR(DAY(H73), "N/A") -> 4 | L73: =IFERROR(TEXT(K73, "[$-en-US]dddd"), "N/A") -> Wednesday | M73: =IF(AND(H73="Error",F73="Error"), "No","Yes") -> Yes
A74: Cake | B74: 3 | C74: 3 | D74: 9 | E74: {=_xlfn.IFS(D74<=5, "$1-5", D74<=10, "$6-10",D74<=15,"$11-15", D74<=20, "$16-20", D74>20, "$20+")} -> $6-10 | F74: Unspecified | G74: Takeaway | H74: 44930 | I74: =IFERROR(YEAR(H74), "N/A") -> 2023 | J74: {=IFERROR(TEXT(H74, "[$-en-US]mmm"), _xleta.N/A)} -> Jan | K74: =IFERROR(DAY(H74), "N/A") -> 4 | L74: =IFERROR(TEXT(K74, "[$-en-US]dddd"), "N/A") -> Wednesday | M74: =IF(AND(H74="Error",F74="Error"), "No","Yes") -> Yes
A75: Coffee | B75: 2 | C75: 2 | D75: 4 | E75: {=_xlfn.IFS(D75<=5, "$1-5", D75<=10, "$6-10",D75<=15,"$11-15", D75<=20, "$16-20", D75>20, "$20+")} -> $1-5 | F75: Unspecified | G75: Unspecified | H75: 44930 | I75: =IFERROR(YEAR(H75), "N/A") -> 2023 | J75: {=IFERROR(TEXT(H75, "[$-en-US]mmm"), _xleta.N/A)} -> Jan | K75: =IFERROR(DAY(H75), "N/A") -> 4 | L75: =IFERROR(TEXT(K75, "[$-en-US]dddd"), "N/A") -> Wednesday | M75: =IF(AND(H75="Error",F75="Error"), "No","Yes") -> Yes
A76: Sandwich | B76: 1 | C76: 4 | D76: 4 | E76: {=_xlfn.IFS(D76<=5, "$1-5", D76<=10, "$6-10",D76<=15,"$11-15", D76<=20, "$16-20", D76>20, "$20+")} -> $1-5 | F76: Digital Wallet | G76: Unspecified | H76: 44930 | I76: =IFERROR(YEAR(H76), "N/A") -> 2023 | J76: {=IFERROR(TEXT(H76, "[$-en-US]mmm"), _xleta.N/A)} -> Jan | K76: =IFERROR(DAY(H76), "N/A") -> 4 | L76: =IFERROR(TEXT(K76, "[$-en-US]dddd"), "N/A") -> Wednesday | M76: =IF(AND(H76="Error",F76="Error"), "No","Yes") -> Yes
A77: Smoothie | B77: 3 | C77: 4 | D77: 12 | E77: {=_xlfn.IFS(D77<=5, "$1-5", D77<=10, "$6-10",D77<=15,"$11-15", D77<=20, "$16-20", D77>20, "$20+")} -> $11-15 | F77: Unspecified | G77: Unspecified | H77: 44930 | I77: =IFERROR(YEAR(H77), "N/A") -> 2023 | J77: {=IFERROR(TEXT(H77, "[$-en-US]mmm"), _xleta.N/A)} -> Jan | K77: =IFERROR(DAY(H77), "N/A") -> 4 | L77: =IFERROR(TEXT(K77, "[$-en-US]dddd"), "N/A") -> Wednesday | M77: =IF(AND(H77="Error",F77="Error"), "No","Yes") -> Yes
A78: Sandwich | B78: 3 | C78: 4 | D78: 12 | E78: {=_xlfn.IFS(D78<=5, "$1-5", D78<=10, "$6-10",D78<=15,"$11-15", D78<=20, "$16-20", D78>20, "$20+")} -> $11-15 | F78: Unspecified | G78: Takeaway | H78: 44930 | I78: =IFERROR(YEAR(H78), "N/A") -> 2023 | J78: {=IFERROR(TEXT(H78, "[$-en-US]mmm"), _xleta.N/A)} -> Jan | K78: =IFERROR(DAY(H78), "N/A") -> 4 | L78: =IFERROR(TEXT(K78, "[$-en-US]dddd"), "N/A") -> Wednesday | M78: =IF(AND(H78="Error",F78="Error"), "No","Yes") -> Yes
A79: Sandwich | B79: 1 | C79: =$D79/$B79 -> 4 | D79: 4 | E79: {=_xlfn.IFS(D79<=5, "$1-5", D79<=10, "$6-10",D79<=15,"$11-15", D79<=20, "$16-20", D79>20, "$20+")} -> $1-5 | F79: Unspecified | G79: In-store | H79: 44930 | I79: =IFERROR(YEAR(H79), "N/A") -> 2023 | J79: {=IFERROR(TEXT(H79, "[$-en-US]mmm"), _xleta.N/A)} -> Jan | K79: =IFERROR(DAY(H79), "N/A") -> 4 | L79: =IFERROR(TEXT(K79, "[$-en-US]dddd"), "N/A") -> Wednesday | M79: =IF(AND(H79="Error",F79="Error"), "No","Yes") -> Yes
A80: Tea | B80: 2 | C80: 1.5 | D80: 3 | E80: {=_xlfn.IFS(D80<=5, "$1-5", D80<=10, "$6-10",D80<=15,"$11-15", D80<=20, "$16-20", D80>20, "$20+")} -> $1-5 | F80: Credit Card | G80: In-store | H80: 44930 | I80: =IFERROR(YEAR(H80), "N/A") -> 2023 | J80: {=IFERROR(TEXT(H80, "[$-en-US]mmm"), _xleta.N/A)} -> Jan | K80: =IFERROR(DAY(H80), "N/A") -> 4 | L80: =IFERROR(TEXT(K80, "[$-en-US]dddd"), "N/A") -> Wednesday | M80: =IF(AND(H80="Error",F80="Error"), "No","Yes") -> Yes
A81: Cake | B81: 1 | C81: 3 | D81: =$B81*$C81 -> 3 | E81: {=_xlfn.IFS(D81<=5, "$1-5", D81<=10, "$6-10",D81<=15,"$11-15", D81<=20, "$16-20", D81>20, "$20+")} -> $1-5 | F81: Unspecified | G81: In-store | H81: 44930 | I81: =IFERROR(YEAR(H81), "N/A") -> 2023 | J81: {=IFERROR(TEXT(H81, "[$-en-US]mmm"), _xleta.N/A)} -> Jan | K81: =IFERROR(DAY(H81), "N/A") -> 4 | L81: =IFERROR(TEXT(K81, "[$-en-US]dddd"), "N/A") -> Wednesday | M81: =IF(AND(H81="Error",F81="Error"), "No","Yes") -> Yes
A82: Smoothie | B82: 5 | C82: 4 | D82: 20 | E82: {=_xlfn.IFS(D82<=5, "$1-5", D82<=10, "$6-10",D82<=15,"$11-15", D82<=20, "$16-20", D82>20, "$20+")} -> $16-20 | F82: Credit Card | G82: In-store | H82: 44930 | I82: =IFERROR(YEAR(H82), "N/A") -> 2023 | J82: {=IFERROR(TEXT(H82, "[$-en-US]mmm"), _xleta.N/A)} -> Jan | K82: =IFERROR(DAY(H82), "N/A") -> 4 | L82: =IFERROR(TEXT(K82, "[$-en-US]dddd"), "N/A") -> Wednesday | M82: =IF(AND(H82="Error",F82="Error"), "No","Yes") -> Yes
A83: Unspecified | B83: 4 | C83: 3 | D83: 12 | E83: {=_xlfn.IFS(D83<=5, "$1-5", D83<=10, "$6-10",D83<=15,"$11-15", D83<=20, "$16-20", D83>20, "$20+")} -> $11-15 | F83: Unspecified | G83: Unspecified | H83: 44930 | I83: =IFERROR(YEAR(H83), "N/A") -> 2023 | J83: {=IFERROR(TEXT(H83, "[$-en-US]mmm"), _xleta.N/A)} -> Jan | K83: =IFERROR(DAY(H83), "N/A") -> 4 | L83: =IFERROR(TEXT(K83, "[$-en-US]dddd"), "N/A") -> Wednesday | M83: =IF(AND(H83="Error",F83="Error"), "No","Yes") -> Yes
A84: Sandwich | B84: 3 | C84: 4 | D84: 12 | E84: {=_xlfn.IFS(D84<=5, "$1-5", D84<=10, "$6-10",D84<=15,"$11-15", D84<=20, "$16-20", D84>20, "$20+")} -> $11-15 | F84: Unspecified | G84: Takeaway | H84: 44930 | I84: =IFERROR(YEAR(H84), "N/A") -> 2023 | J84: {=IFERROR(TEXT(H84, "[$-en-US]mmm"), _xleta.N/A)} -> Jan | K84: =IFERROR(DAY(H84), "N/A") -> 4 | L84: =IFERROR(TEXT(K84, "[$-en-US]dddd"), "N/A") -> Wednesday | M84: =IF(AND(H84="Error",F84="Error"), "No","Yes") -> Yes
A85: Juice | B85: 2 | C85: 3 | D85: 6 | E85: {=_xlfn.IFS(D85<=5, "$1-5", D85<=10, "$6-10",D85<=15,"$11-15", D85<=20, "$16-20", D85>20, "$20+")} -> $6-10 | F85: Digital Wallet | G85: Unspecified | H85: 44930 | I85: =IFERROR(YEAR(H85), "N/A") -> 2023 | J85: {=IFERROR(TEXT(H85, "[$-en-US]mmm"), _xleta.N/A)} -> Jan | K85: =IFERROR(DAY(H85), "N/A") -> 4 | L85: =IFERROR(TEXT(K85, "[$-en-US]dddd"), "N/A") -> Wednesday | M85: =IF(AND(H85="Error",F85="Error"), "No","Yes") -> Yes
A86: Salad | B86: 1 | C86: 5 | D86: 5 | E86: {=_xlfn.IFS(D86<=5, "$1-5", D86<=10, "$6-10",D86<=15,"$11-15", D86<=20, "$16-20", D86>20, "$20+")} -> $1-5 | F86: Unspecified | G86: Unspecified | H86: 44930 | I86: =IFERROR(YEAR(H86), "N/A") -> 2023 | J86: {=IFERROR(TEXT(H86, "[$-en-US]mmm"), _xleta.N/A)} -> Jan | K86: =IFERROR(DAY(H86), "N/A") -> 4 | L86: =IFERROR(TEXT(K86, "[$-en-US]dddd"), "N/A") -> Wednesday | M86: =IF(AND(H86="Error",F86="Error"), "No","Yes") -> Yes
A87: Cookie | B87: 4 | C87: 1 | D87: 4 | E87: {=_xlfn.IFS(D87<=5, "$1-5", D87<=10, "$6-10",D87<=15,"$11-15", D87<=20, "$16-20", D87>20, "$20+")} -> $1-5 | F87: Unspecified | G87: Error | H87: 44930 | I87: =IFERROR(YEAR(H87), "N/A") -> 2023 | J87: {=IFERROR(TEXT(H87, "[$-en-US]mmm"), _xleta.N/A)} -> Jan | K87: =IFERROR(DAY(H87), "N/A") -> 4 | L87: =IFERROR(TEXT(K87, "[$-en-US]dddd"), "N/A") -> Wednesday | M87: =IF(AND(H87="Error",F87="Error"), "No","Yes") -> Yes
A88: Salad | B88: 3 | C88: 5 | D88: 15 | E88: {=_xlfn.IFS(D88<=5, "$1-5", D88<=10, "$6-10",D88<=15,"$11-15", D88<=20, "$16-20", D88>20, "$20+")} -> $11-15 | F88: Cash | G88: Unspecified | H88: 44930 | I88: =IFERROR(YEAR(H88), "N/A") -> 2023 | J88: {=IFERROR(TEXT(H88, "[$-en-US]mmm"), _xleta.N/A)} -> Jan | K88: =IFERROR(DAY(H88), "N/A") -> 4 | L88: =IFERROR(TEXT(K88, "[$-en-US]dddd"), "N/A") -> Wednesday | M88: =IF(AND(H88="Error",F88="Error"), "No","Yes") -> Yes
A89: Coffee | B89: 1 | C89: 2 | D89: 2 | E89: {=_xlfn.IFS(D89<=5, "$1-5", D89<=10, "$6-10",D89<=15,"$11-15", D89<=20, "$16-20", D89>20, "$20+")} -> $1-5 | F89: Digital Wallet | G89: Error | H89: 44930 | I89: =IFERROR(YEAR(H89), "N/A") -> 2023 | J89: {=IFERROR(TEXT(H89, "[$-en-US]mmm"), _xleta.N/A)} -> Jan | K89: =IFERROR(DAY(H89), "N/A") -> 4 | L89: =IFERROR(TEXT(K89, "[$-en-US]dddd"), "N/A") -> Wednesday | M89: =IF(AND(H89="Error",F89="Error"), "No","Yes") -> Yes
A90: Salad | B90: 5 | C90: 5 | D90: 25 | E90: {=_xlfn.IFS(D90<=5, "$1-5", D90<=10, "$6-10",D90<=15,"$11-15", D90<=20, "$16-20", D90>20, "$20+")} -> $20+ | F90: Digital Wallet | G90: In-store | H90: 44930 | I90: =IFERROR(YEAR(H90), "N/A") -> 2023 | J90: {=IFERROR(TEXT(H90, "[$-en-US]mmm"), _xleta.N/A)} -> Jan | K90: =IFERROR(DAY(H90), "N/A") -> 4 | L90: =IFERROR(TEXT(K90, "[$-en-US]dddd"), "N/A") -> Wednesday | M90: =IF(AND(H90="Error",F90="Error"), "No","Yes") -> Yes
A91: Coffee | B91: 5 | C91: 2 | D91: 10 | E91: {=_xlfn.IFS(D91<=5, "$1-5", D91<=10, "$6-10",D91<=15,"$11-15", D91<=20, "$16-20", D91>20, "$20+")} -> $6-10 | F91: Cash | G91: In-store | H91: 44931 | I91: =IFERROR(YEAR(H91), "N/A") -> 2023 | J91: {=IFERROR(TEXT(H91, "[$-en-US]mmm"), _xleta.N/A)} -> Jan | K91: =IFERROR(DAY(H91), "N/A") -> 5 | L91: =IFERROR(TEXT(K91, "[$-en-US]dddd"), "N/A") -> Thursday | M91: =IF(AND(H91="Error",F91="Error"), "No","Yes") -> Yes
A92: Cake | B92: 2 | C92: 3 | D92: 6 | E92: {=_xlfn.IFS(D92<=5, "$1-5", D92<=10, "$6-10",D92<=15,"$11-15", D92<=20, "$16-20", D92>20, "$20+")} -> $6-10 | F92: Cash | G92: Takeaway | H92: 44931 | I92: =IFERROR(YEAR(H92), "N/A") -> 2023 | J92: {=IFERROR(TEXT(H92, "[$-en-US]mmm"), _xleta.N/A)} -> Jan | K92: =IFERROR(DAY(H92), "N/A") -> 5 | L92: =IFERROR(TEXT(K92, "[$-en-US]dddd"), "N/A") -> Thursday | M92: =IF(AND(H92="Error",F92="Error"), "No","Yes") -> Yes
A93: Sandwich | B93: 4 | C93: 4 | D93: 16 | E93: {=_xlfn.IFS(D93<=5, "$1-5", D93<=10, "$6-10",D93<=15,"$11-15", D93<=20, "$16-20", D93>20, "$20+")} -> $16-20 | F93: Credit Card | G93: Takeaway | H93: 44931 | I93: =IFERROR(YEAR(H93), "N/A") -> 2023 | J93: {=IFERROR(TEXT(H93, "[$-en-US]mmm"), _xleta.N/A)} -> Jan | K93: =IFERROR(DAY(H93), "N/A") -> 5 | L93: =IFERROR(TEXT(K93, "[$-en-US]dddd"), "N/A") -> Thursday | M93: =IF(AND(H93="Error",F93="Error"), "No","Yes") -> Yes
A94: Tea | B94: 2 | C94: 1.5 | D94: 3 | E94: {=_xlfn.IFS(D94<=5, "$1-5", D94<=10, "$6-10",D94<=15,"$11-15", D94<=20, "$16-20", D94>20, "$20+")} -> $1-5 | F94: Unspecified | G94: Unspecified | H94: 44931 | I94: =IFERROR(YEAR(H94), "N/A") -> 2023 | J94: {=IFERROR(TEXT(H94, "[$-en-US]mmm"), _xleta.N/A)} -> Jan | K94: =IFERROR(DAY(H94), "N/A") -> 5 | L94: =IFERROR(TEXT(K94, "[$-en-US]dddd"), "N/A") -> Thursday | M94: =IF(AND(H94="Error",F94="Error"), "No","Yes") -> Yes
A95: Sandwich | B95: =D95/C95 -> 5 | C95: =_xlfn.XLOOKUP(A95,'Item Price'!A:A,'Item Price'!B:B) -> 4 | D95: 20 | E95: {=_xlfn.IFS(D95<=5, "$1-5", D95<=10, "$6-10",D95<=15,"$11-15", D95<=20, "$16-20", D95>20, "$20+")} -> $16-20 | F95: Error | G95: Takeaway | H95: 44931 | I95: =IFERROR(YEAR(H95), "N/A") -> 2023 | J95: {=IFERROR(TEXT(H95, "[$-en-US]mmm"), _xleta.N/A)} -> Jan | K95: =IFERROR(DAY(H95), "N/A") -> 5 | L95: =IFERROR(TEXT(K95, "[$-en-US]dddd"), "N/A") -> Thursday | M95: =IF(AND(H95="Error",F95="Error"), "No","Yes") -> Yes
A96: Sandwich | B96: 4 | C96: 4 | D96: 16 | E96: {=_xlfn.IFS(D96<=5, "$1-5", D96<=10, "$6-10",D96<=15,"$11-15", D96<=20, "$16-20", D96>20, "$20+")} -> $16-20 | F96: Cash | G96: In-store | H96: 44931 | I96: =IFERROR(YEAR(H96), "N/A") -> 2023 | J96: {=IFERROR(TEXT(H96, "[$-en-US]mmm"), _xleta.N/A)} -> Jan | K96: =IFERROR(DAY(H96), "N/A") -> 5 | L96: =IFERROR(TEXT(K96, "[$-en-US]dddd"), "N/A") -> Thursday | M96: =IF(AND(H96="Error",F96="Error"), "No","Yes") -> Yes
A97: Coffee | B97: 4 | C97: 2 | D97: 8 | E97: {=_xlfn.IFS(D97<=5, "$1-5", D97<=10, "$6-10",D97<=15,"$11-15", D97<=20, "$16-20", D97>20, "$20+")} -> $6-10 | F97: Unspecified | G97: Error | H97: 44931 | I97: =IFERROR(YEAR(H97), "N/A") -> 2023 | J97: {=IFERROR(TEXT(H97, "[$-en-US]mmm"), _xleta.N/A)} -> Jan | K97: =IFERROR(DAY(H97), "N/A") -> 5 | L97: =IFERROR(TEXT(K97, "[$-en-US]dddd"), "N/A") -> Thursday | M97: =IF(AND(H97="Error",F97="Error"), "No","Yes") -> Yes
A98: Cookie | B98: 2 | C98: 1 | D98: 2 | E98: {=_xlfn.IFS(D98<=5, "$1-5", D98<=10, "$6-10",D98<=15,"$11-15", D98<=20, "$16-20", D98>20, "$20+")} -> $1-5 | F98: Cash | G98: Takeaway | H98: 44931 | I98: =IFERROR(YEAR(H98), "N/A") -> 2023 | J98: {=IFERROR(TEXT(H98, "[$-en-US]mmm"), _xleta.N/A)} -> Jan | K98: =IFERROR(DAY(H98), "N/A") -> 5 | L98: =IFERROR(TEXT(K98, "[$-en-US]dddd"), "N/A") -> Thursday | M98: =IF(AND(H98="Error",F98="Error"), "No","Yes") -> Yes
A99: Sandwich | B99: 1 | C99: 4 | D99: 4 | E99: {=_xlfn.IFS(D99<=5, "$1-5", D99<=10, "$6-10",D99<=15,"$11-15", D99<=20, "$16-20", D99>20, "$20+")} -> $1-5 | F99: Unspecified | G99: Unspecified | H99: 44931 | I99: =IFERROR(YEAR(H99), "N/A") -> 2023 | J99: {=IFERROR(TEXT(H99, "[$-en-US]mmm"), _xleta.N/A)} -> Jan | K99: =IFERROR(DAY(H99), "N/A") -> 5 | L99: =IFERROR(TEXT(K99, "[$-en-US]dddd"), "N/A") -> Thursday | M99: =IF(AND(H99="Error",F99="Error"), "No","Yes") -> Yes
A100: Smoothie | B100: 1 | C100: 4 | D100: 4 | E100: {=_xlfn.IFS(D100<=5, "$1-5", D100<=10, "$6-10",D100<=15,"$11-15", D100<=20, "$16-20", D100>20, "$20+")} -> $1-5 | F100: Error | G100: Takeaway | H100: 44931 | I100: =IFERROR(YEAR(H100), "N/A") -> 2023 | J100: {=IFERROR(TEXT(H100, "[$-en-US]mmm"), _xleta.N/A)} -> Jan | K100: =IFERROR(DAY(H100), "N/A") -> 5 | L100: =IFERROR(TEXT(K100, "[$-en-US]dddd"), "N/A") -> Thursday | M100: =IF(AND(H100="Error",F100="Error"), "No","Yes") -> Yes
...

Sheet Avg Daily Sales (month)
A1: Total Spent | B1: Date | C1: Month | F1: Month | G1: Number of days | H1: Total Sales | M1: 2023 Sales Trend
A2: 10 | B2: 44927 | C2: Jan | F2: January | G2: 31 | H2: =N3/G2 -> 234 | M2: Row Labels | N2: Sum of Total Spent
A3: 9 | B3: 44927 | C3: Jan | F3: February | G3: 28 | H3: =N4/G3 -> 237.28571 | M3: Jan | N3: 7254
A4: 20 | B4: 44927 | C4: Jan | F4: March | G4: 31 | H4: =N5/G4 -> 232.77419 | M4: Feb | N4: 6644
A5: 15 | B5: 44927 | C5: Jan | F5: April | G5: 30 | H5: =N6/G5 -> 239.3 | M5: Mar | N5: 7216
A6: 20 | B6: 44927 | C6: Jan | F6: May | G6: 31 | H6: =N7/G6 -> 224.43548 | M6: Apr | N6: 7179
A7: 4.5 | B7: 44927 | C7: Jan | F7: June | G7: 30 | H7: =N8/G7 -> 245.1 | M7: May | N7: 6957.5
A8: 10 | B8: 44927 | C8: Jan | F8: July | G8: 31 | H8: =N9/G8 -> 221.85484 | M8: Jun | N8: 7353
A9: 10 | B9: 44927 | C9: Jan | F9: August | G9: 31 | H9: =N10/G9 -> 229.43548 | M9: Jul | N9: 6877.5
A10: 12 | B10: 44927 | C10: Jan | F10: September | G10: 30 | H10: =N11/G10 -> 229.03333 | M10: Aug | N10: 7112.5
A11: 4 | B11: 44927 | C11: Jan | F11: October | G11: 31 | H11: =N12/G11 -> 235.93548 | M11: Sep | N11: 6871
A12: 12 | B12: 44927 | C12: Jan | F12: November | G12: 30 | H12: =N13/G12 -> 232.23333 | M12: Oct | N12: 7314
A13: 8 | B13: 44927 | C13: Jan | F13: December | G13: 31 | H13: =N14/G13 -> 231.51613 | M13: Nov | N13: 6967
A14: 2 | B14: 44927 | C14: Jan | M14: Dec | N14: 7177
A15: 4 | B15: 44927 | C15: Jan | M15: Grand Total | N15: 84922.5
A16: 4 | B16: 44927 | C16: Jan
A17: 7.5 | B17: 44927 | C17: Jan | F17: Month | G17: Total Sales
A18: 3 | B18: 44927 | C18: Jan | F18: January | G18: 234 | M18: 2023 Traffic Trend
A19: 4 | B19: 44927 | C19: Jan | F19: February | G19: 237.28571 | M19: Row Labels | N19: Count of Total Spent
A20: 8 | B20: 44927 | C20: Jan | F20: March | G20: 232.77419 | M20: Jan | N20: 818
A21: 9 | B21: 44928 | C21: Jan | F21: April | G21: 239.3 | M21: Feb | N21: 727
A22: 20 | B22: 44928 | C22: Jan | F22: May | G22: 224.43548 | M22: Mar | N22: 827
A23: 4 | B23: 44928 | C23: Jan | F23: June | G23: 245.1 | M23: Apr | N23: 774
A24: 20 | B24: 44928 | C24: Jan | F24: July | G24: 221.85484 | M24: May | N24: 777
A25: 4 | B25: 44928 | C25: Jan | F25: August | G25: 229.43548 | M25: Jun | N25: 818
A26: 10 | B26: 44928 | C26: Jan | F26: September | G26: 229.03333 | M26: Jul | N26: 791
A27: 20 | B27: 44928 | C27: Jan | F27: October | G27: 235.93548 | M27: Aug | N27: 803
A28: 20 | B28: 44928 | C28: Jan | F28: November | G28: 232.23333 | M28: Sep | N28: 788
A29: 8 | B29: 44928 | C29: Jan | F29: December | G29: 231.51613 | M29: Oct | N29: 838
A30: 5 | B30: 44928 | C30: Jan | M30: Nov | N30: 784
A31: 6 | B31: 44928 | C31: Jan | F31: Month | G31: Number of days | H31: Average Daily Traffic | M31: Dec | N31: 795
A32: 8 | B32: 44928 | C32: Jan | F32: January | G32: 31 | H32: =N20/G32 -> 26.387097 | M32: Grand Total | N32: 9540
A33: 3 | B33: 44928 | C33: Jan | F33: February | G33: 28 | H33: =N21/G33 -> 25.964286
A34: 4 | B34: 44928 | C34: Jan | F34: March | G34: 31 | H34: =N22/G34 -> 26.677419
A35: 6 | B35: 44928 | C35: Jan | F35: April | G35: 30 | H35: =N23/G35 -> 25.8
A36: 12 | B36: 44928 | C36: Jan | F36: May | G36: 31 | H36: =N24/G36 -> 25.064516
A37: 16 | B37: 44928 | C37: Jan | F37: June | G37: 30 | H37: =N25/G37 -> 27.266667
A38: 10 | B38: 44928 | C38: Jan | F38: July | G38: 31 | H38: =N26/G38 -> 25.516129
A39: 3 | B39: 44928 | C39: Jan | F39: August | G39: 31 | H39: =N27/G39 -> 25.903226
A40: 1.5 | B40: 44928 | C40: Jan | F40: September | G40: 30 | H40: =N28/G40 -> 26.266667
A41: 1.5 | B41: 44928 | C41: Jan | F41: October | G41: 31 | H41: =N29/G41 -> 27.032258
A42: 7.5 | B42: 44929 | C42: Jan | F42: November | G42: 30 | H42: =N30/G42 -> 26.133333
A43: 3 | B43: 44929 | C43: Jan | F43: December | G43: 31 | H43: =N31/G43 -> 25.645161
A44: 12 | B44: 44929 | C44: Jan
A45: 25 | B45: 44929 | C45: Jan
A46: 16 | B46: 44929 | C46: Jan
A47: 12 | B47: 44929 | C47: Jan
A48: 2 | B48: 44929 | C48: Jan
A49: 6 | B49: 44929 | C49: Jan
A50: 15 | B50: 44929 | C50: Jan
A51: 12 | B51: 44929 | C51: Jan
A52: 1 | B52: 44929 | C52: Jan
A53: 8 | B53: 44929 | C53: Jan
A54: 3 | B54: 44929 | C54: Jan
A55: 1 | B55: 44929 | C55: Jan
... A9540: 3 | B9540: 45291 | C9540: Dec
A9541: 5 | B9541: Error | C9541: Dec
A9542: 8 | B9542: Error | C9542: Error
A9543: 12 | B9543: Error | C9543: Error
A9544: 5 | B9544: Error | C9544: Error
A9545: 12 | B9545: Error | C9545: Error
A9546: 2 | B9546: Error | C9546: Error
A9547: 8 | B9547: Error | C9547: Error
A9548: 15 | B9548: Error | C9548: Error
A9549: 16 | B9549: Error | C9549: Error
A9550: 1 | B9550: Error | C9550: Error
A9551: 3 | B9551: Error | C9551: Error
A9552: 6 | B9552: Error | C9552: Error
... A10000: 12 | B10000: Unspecified | C10000: Unspecified
A10001: 15 | C10001: Unspecified

Sheet Potential Sales
A1: Item | B1: Quantity | C1: Price Per Unit | D1: Total Spent | E1: Spent Group | F1: Potential Sales | I1: Potential Sales Increase by pursuring Spent Group $1-5 buy one more item
A2: Juice | B2: 5 | C2: 3 | D2: 15 | E2: $11-15 | F2: =IF(E2="$1-5", D2+3, D2) -> 15 | I2: =(SUM(F:F)-SUM(D:D))/SUM(D:D) -> 0.12369189
A3: Unspecified | B3: 4 | C3: 3 | D3: 12 | E3: $11-15 | F3: =IF(E3="$1-5", D3+3, D3) -> 12
A4: Cake | B4: 4 | C4: 3 | D4: 12 | E4: $11-15 | F4: =IF(E4="$1-5", D4+3, D4) -> 12
A5: Cake | B5: 4 | C5: 3 | D5: 12 | E5: $11-15 | F5: =IF(E5="$1-5", D5+3, D5) -> 12
A6: Cake | B6: 4 | C6: 3 | D6: 12 | E6: $11-15 | F6: =IF(E6="$1-5", D6+3, D6) -> 12
A7: Juice | B7: 4 | C7: 3 | D7: 12 | E7: $11-15 | F7: =IF(E7="$1-5", D7+3, D7) -> 12
A8: Cake | B8: 5 | C8: 3 | D8: 15 | E8: $11-15 | F8: =IF(E8="$1-5", D8+3, D8) -> 15
A9: Juice | B9: 4 | C9: 3 | D9: 12 | E9: $11-15 | F9: =IF(E9="$1-5", D9+3, D9) -> 12
A10: Salad | B10: 3 | C10: 5 | D10: 15 | E10: $11-15 | F10: =IF(E10="$1-5", D10+3, D10) -> 15
A11: Smoothie | B11: 3 | C11: 4 | D11: 12 | E11: $11-15 | F11: =IF(E11="$1-5", D11+3, D11) -> 12
A12: Unspecified | B12: 3 | C12: 4 | D12: 12 | E12: $11-15 | F12: =IF(E12="$1-5", D12+3, D12) -> 12
A13: Juice | B13: 4 | C13: 3 | D13: 12 | E13: $11-15 | F13: =IF(E13="$1-5", D13+3, D13) -> 12
A14: Cake | B14: 5 | C14: 3 | D14: 15 | E14: $11-15 | F14: =IF(E14="$1-5", D14+3, D14) -> 15
... A2147: Tea | B2147: 2 | C2147: 1.5 | D2147: 3 | E2147: $1-5 | F2147: =IF(E2147="$1-5", D2147+3, D2147) -> 6
A2148: Unspecified | B2148: 4 | C2148: Unknown | D2148: 0 | E2148: $1-5 | F2148: =IF(E2148="$1-5", D2148+3, D2148) -> 3
A2149: Smoothie | B2149: 1 | C2149: 4 | D2149: 4 | E2149: $1-5 | F2149: =IF(E2149="$1-5", D2149+3, D2149) -> 7
A2150: Tea | B2150: 3 | C2150: 1.5 | D2150: 4.5 | E2150: $1-5 | F2150: =IF(E2150="$1-5", D2150+3, D2150) -> 7.5
A2151: Coffee | B2151: 1 | C2151: 2 | D2151: 2 | E2151: $1-5 | F2151: =IF(E2151="$1-5", D2151+3, D2151) -> 5
A2152: Cake | B2152: 1 | C2152: 3 | D2152: 3 | E2152: $1-5 | F2152: =IF(E2152="$1-5", D2152+3, D2152) -> 6
A2153: Salad | B2153: 1 | C2153: 5 | D2153: 5 | E2153: $1-5 | F2153: =IF(E2153="$1-5", D2153+3, D2153) -> 8
A2154: Sandwich | B2154: 1 | C2154: 4 | D2154: 4 | E2154: $1-5 | F2154: =IF(E2154="$1-5", D2154+3, D2154) -> 7
A2155: Coffee | B2155: 1 | C2155: 2 | D2155: 2 | E2155: $1-5 | F2155: =IF(E2155="$1-5", D2155+3, D2155) -> 5
A2156: Tea | B2156: 1 | C2156: 1.5 | D2156: 1.5 | E2156: $1-5 | F2156: =IF(E2156="$1-5", D2156+3, D2156) -> 4.5
A2157: Smoothie | B2157: 1 | C2157: 4 | D2157: 4 | E2157: $1-5 | F2157: =IF(E2157="$1-5", D2157+3, D2157) -> 7
A2158: Cookie | B2158: 4 | C2158: 1 | D2158: 4 | E2158: $1-5 | F2158: =IF(E2158="$1-5", D2158+3, D2158) -> 7
A2159: Coffee | B2159: 1 | C2159: 2 | D2159: 2 | E2159: $1-5 | F2159: =IF(E2159="$1-5", D2159+3, D2159) -> 5
A2160: Cookie | B2160: 1 | C2160: 1 | D2160: 1 | E2160: $1-5 | F2160: =IF(E2160="$1-5", D2160+3, D2160) -> 4
... A5066: Coffee | B5066: 2 | C5066: 2 | D5066: 4 | E5066: $1-5 | F5066: =IF(E5066="$1-5", D5066+3, D5066) -> 7
A5067: Unspecified | B5067: 4 | C5067: Unknown | D5067: 0 | E5067: $1-5 | F5067: =IF(E5067="$1-5", D5067+3, D5067) -> 3
A5068: Cookie | B5068: 1 | C5068: 1 | D5068: 1 | E5068: $1-5 | F5068: =IF(E5068="$1-5", D5068+3, D5068) -> 4
A5069: Coffee | B5069: 1 | C5069: 2 | D5069: 2 | E5069: $1-5 | F5069: =IF(E5069="$1-5", D5069+3, D5069) -> 5
A5070: Coffee | B5070: 1 | C5070: 2 | D5070: 2 | E5070: $1-5 | F5070: =IF(E5070="$1-5", D5070+3, D5070) -> 5
A5071: Cookie | B5071: 5 | C5071: 1 | D5071: 5 | E5071: $1-5 | F5071: =IF(E5071="$1-5", D5071+3, D5071) -> 8
A5072: Juice | B5072: 1 | C5072: 3 | D5072: 3 | E5072: $1-5 | F5072: =IF(E5072="$1-5", D5072+3, D5072) -> 6
A5073: Cookie | B5073: 2 | C5073: 1 | D5073: 2 | E5073: $1-5 | F5073: =IF(E5073="$1-5", D5073+3, D5073) -> 5
A5074: Juice | B5074: 1 | C5074: 3 | D5074: 3 | E5074: $1-5 | F5074: =IF(E5074="$1-5", D5074+3, D5074) -> 6
A5075: Cookie | B5075: 1 | C5075: 1 | D5075: 1 | E5075: $1-5 | F5075: =IF(E5075="$1-5", D5075+3, D5075) -> 4
A5076: Cookie | B5076: 5 | C5076: 1 | D5076: 5 | E5076: $1-5 | F5076: =IF(E5076="$1-5", D5076+3, D5076) -> 8
A5077: Tea | B5077: 1 | C5077: 1.5 | D5077: 1.5 | E5077: $1-5 | F5077: =IF(E5077="$1-5", D5077+3, D5077) -> 4.5
A5078: Coffee | B5078: 2 | C5078: 2 | D5078: 4 | E5078: $1-5 | F5078: =IF(E5078="$1-5", D5078+3, D5078) -> 7
A5079: Cookie | B5079: 2 | C5079: 1 | D5079: 2 | E5079: $1-5 | F5079: =IF(E5079="$1-5", D5079+3, D5079) -> 5
... A5112: Cookie | B5112: 1 | C5112: 1 | D5112: 1 | E5112: $1-5 | F5112: =IF(E5112="$1-5", D5112+3, D5112) -> 4
A5113: Unspecified | B5113: 2 | C5113: Unknown | D5113: 0 | E5113: $1-5 | F5113: =IF(E5113="$1-5", D5113+3, D5113) -> 3
A5114: Cookie | B5114: 2 | C5114: 1 | D5114: 2 | E5114: $1-5 | F5114: =IF(E5114="$1-5", D5114+3, D5114) -> 5
A5115: Tea | B5115: 3 | C5115: 1.5 | D5115: 4.5 | E5115: $1-5 | F5115: =IF(E5115="$1-5", D5115+3, D5115) -> 7.5
A5116: Cookie | B5116: 5 | C5116: 1 | D5116: 5 | E5116: $1-5 | F5116: =IF(E5116="$1-5", D5116+3, D5116) -> 8
A5117: Tea | B5117: 3 | C5117: 1.5 | D5117: 4.5 | E5117: $1-5 | F5117: =IF(E5117="$1-5", D5117+3, D5117) -> 7.5
A5118: Juice | B5118: 1 | C5118: 3 | D5118: 3 | E5118: $1-5 | F5118: =IF(E5118="$1-5", D5118+3, D5118) -> 6
A5119: Cookie | B5119: 3 | C5119: 1 | D5119: 3 | E5119: $1-5 | F5119: =IF(E5119="$1-5", D5119+3, D5119) -> 6
A5120: Cookie | B5120: 4 | C5120: 1 | D5120: 4 | E5120: $1-5 | F5120: =IF(E5120="$1-5", D5120+3, D5120) -> 7
A5121: Coffee | B5121: 1 | C5121: 2 | D5121: 2 | E5121: $1-5 | F5121: =IF(E5121="$1-5", D5121+3, D5121) -> 5
A5122: Cookie | B5122: 5 | C5122: 1 | D5122: 5 | E5122: $1-5 | F5122: =IF(E5122="$1-5", D5122+3, D5122) -> 8
A5123: Cookie | B5123: 1 | C5123: 1 | D5123: 1 | E5123: $1-5 | F5123: =IF(E5123="$1-5", D5123+3, D5123) -> 4
A5124: Cookie | B5124: 1 | C5124: 1 | D5124: 1 | E5124: $1-5 | F5124: =IF(E5124="$1-5", D5124+3, D5124) -> 4
A5125: Coffee | B5125: 2 | C5125: 2 | D5125: 4 | E5125: $1-5 | F5125: =IF(E5125="$1-5", D5125+3, D5125) -> 7
... A6196: Smoothie | B6196: 5 | C6196: 4 | D6196: 20 | E6196: $16-20 | F6196: =IF(E6196="$1-5", D6196+3, D6196) -> 20
A6197: Unspecified | B6197: 0 | C6197: Unknown | D6197: 20 | E6197: $16-20 | F6197: =IF(E6197="$1-5", D6197+3, D6197) -> 20
A6198: Salad | B6198: 4 | C6198: 5 | D6198: 20 | E6198: $16-20 | F6198: =IF(E6198="$1-5", D6198+3, D6198) -> 20
A6199: Smoothie | B6199: 5 | C6199: 4 | D6199: 20 | E6199: $16-20 | F6199: =IF(E6199="$1-5", D6199+3, D6199) -> 20
A6200: Salad | B6200: 4 | C6200: 5 | D6200: 20 | E6200: $16-20 | F6200: =IF(E6200="$1-5", D6200+3, D6200) -> 20
A6201: Smoothie | B6201: 4 | C6201: 4 | D6201: 16 | E6201: $16-20 | F6201: =IF(E6201="$1-5", D6201+3, D6201) -> 16
A6202: Salad | B6202: 4 | C6202: 5 | D6202: 20 | E6202: $16-20 | F6202: =IF(E6202="$1-5", D6202+3, D6202) -> 20
A6203: Sandwich | B6203: 5 | C6203: 4 | D6203: 20 | E6203: $16-20 | F6203: =IF(E6203="$1-5", D6203+3, D6203) -> 20
A6204: Unspecified | B6204: 4 | C6204: 4 | D6204: 16 | E6204: $16-20 | F6204: =IF(E6204="$1-5", D6204+3, D6204) -> 16
A6205: Unspecified | B6205: 5 | C6205: 4 | D6205: 20 | E6205: $16-20 | F6205: =IF(E6205="$1-5", D6205+3, D6205) -> 20
A6206: Unspecified | B6206: 4 | C6206: 4 | D6206: 16 | E6206: $16-20 | F6206: =IF(E6206="$1-5", D6206+3, D6206) -> 16
A6207: Unspecified | B6207: 4 | C6207: 4 | D6207: 16 | E6207: $16-20 | F6207: =IF(E6207="$1-5", D6207+3, D6207) -> 16
A6208: Smoothie | B6208: 5 | C6208: 4 | D6208: 20 | E6208: $16-20 | F6208: =IF(E6208="$1-5", D6208+3, D6208) -> 20
A6209: Smoothie | B6209: 5 | C6209: 4 | D6209: 20 | E6209: $16-20 | F6209: =IF(E6209="$1-5", D6209+3, D6209) -> 20
... A6787: Salad | B6787: 5 | C6787: 5 | D6787: 25 | E6787: $20+ | F6787: =IF(E6787="$1-5", D6787+3, D6787) -> 25
A6788: Unspecified | B6788: 0 | C6788: Unknown | D6788: 25 | E6788: $20+ | F6788: =IF(E6788="$1-5", D6788+3, D6788) -> 25
A6789: Salad | B6789: 5 | C6789: 5 | D6789: 25 | E6789: $20+ | F6789: =IF(E6789="$1-5", D6789+3, D6789) -> 25
A6790: Salad | B6790: 5 | C6790: 5 | D6790: 25 | E6790: $20+ | F6790: =IF(E6790="$1-5", D6790+3, D6790) -> 25
A6791: Salad | B6791: 5 | C6791: 5 | D6791: 25 | E6791: $20+ | F6791: =IF(E6791="$1-5", D6791+3, D6791) -> 25
A6792: Salad | B6792: 5 | C6792: 5 | D6792: 25 | E6792: $20+ | F6792: =IF(E6792="$1-5", D6792+3, D6792) -> 25
A6793: Salad | B6793: 5 | C6793: 5 | D6793: 25 | E6793: $20+ | F6793: =IF(E6793="$1-5", D6793+3, D6793) -> 25
A6794: Salad | B6794: 5 | C6794: 5 | D6794: 25 | E6794: $20+ | F6794: =IF(E6794="$1-5", D6794+3, D6794) -> 25
A6795: Salad | B6795: 5 | C6795: 5 | D6795: 25 | E6795: $20+ | F6795: =IF(E6795="$1-5", D6795+3, D6795) -> 25
A6796: Salad | B6796: 5 | C6796: 5 | D6796: 25 | E6796: $20+ | F6796: =IF(E6796="$1-5", D6796+3, D6796) -> 25
A6797: Salad | B6797: 5 | C6797: 5 | D6797: 25 | E6797: $20+ | F6797: =IF(E6797="$1-5", D6797+3, D6797) -> 25
A6798: Salad | B6798: 5 | C6798: 5 | D6798: 25 | E6798: $20+ | F6798: =IF(E6798="$1-5", D6798+3, D6798) -> 25
A6799: Salad | B6799: 5 | C6799: 5 | D6799: 25 | E6799: $20+ | F6799: =IF(E6799="$1-5", D6799+3, D6799) -> 25
A6800: Salad | B6800: 5 | C6800: 5 | D6800: 25 | E6800: $20+ | F6800: =IF(E6800="$1-5", D6800+3, D6800) -> 25
... A9725: Juice | B9725: 2 | C9725: 3 | D9725: 6 | E9725: $6-10 | F9725: =IF(E9725="$1-5", D9725+3, D9725) -> 6
A9726: Unspecified | B9726: 0 | C9726: Unknown | D9726: 9 | E9726: $6-10 | F9726: =IF(E9726="$1-5", D9726+3, D9726) -> 9
A9727: Cake | B9727: 3 | C9727: 3 | D9727: 9 | E9727: $6-10 | F9727: =IF(E9727="$1-5", D9727+3, D9727) -> 9
A9728: Smoothie | B9728: 2 | C9728: 4 | D9728: 8 | E9728: $6-10 | F9728: =IF(E9728="$1-5", D9728+3, D9728) -> 8
A9729: Sandwich | B9729: 2 | C9729: 4 | D9729: 8 | E9729: $6-10 | F9729: =IF(E9729="$1-5", D9729+3, D9729) -> 8
A9730: Cake | B9730: 2 | C9730: 3 | D9730: 6 | E9730: $6-10 | F9730: =IF(E9730="$1-5", D9730+3, D9730) -> 6
A9731: Cake | B9731: 2 | C9731: 3 | D9731: 6 | E9731: $6-10 | F9731: =IF(E9731="$1-5", D9731+3, D9731) -> 6
A9732: Tea | B9732: 5 | C9732: 1.5 | D9732: 7.5 | E9732: $6-10 | F9732: =IF(E9732="$1-5", D9732+3, D9732) -> 7.5
A9733: Coffee | B9733: 3 | C9733: 2 | D9733: 6 | E9733: $6-10 | F9733: =IF(E9733="$1-5", D9733+3, D9733) -> 6
A9734: Cake | B9734: 3 | C9734: 3 | D9734: 9 | E9734: $6-10 | F9734: =IF(E9734="$1-5", D9734+3, D9734) -> 9
A9735: Sandwich | B9735: 2 | C9735: 4 | D9735: 8 | E9735: $6-10 | F9735: =IF(E9735="$1-5", D9735+3, D9735) -> 8
A9736: Juice | B9736: 2 | C9736: 3 | D9736: 6 | E9736: $6-10 | F9736: =IF(E9736="$1-5", D9736+3, D9736) -> 6
A9737: Coffee | B9737: 3 | C9737: 2 | D9737: 6 | E9737: $6-10 | F9737: =IF(E9737="$1-5", D9737+3, D9737) -> 6
A9738: Cake | B9738: 2 | C9738: 3 | D9738: 6 | E9738: $6-10 | F9738: =IF(E9738="$1-5", D9738+3, D9738) -> 6
... A9997: Juice | B9997: 3 | C9997: 3 | D9997: 9 | E9997: $6-10 | F9997: =IF(E9997="$1-5", D9997+3, D9997) -> 9

Sheet Item Price
A1: Item | B1: Item Price
A2: Cookie | B2: 1
A3: Tea | B3: 1.5
A4: Coffee | B4: 2
A5: Cake | B5: 3
A6: Juice | B6: 3
A7: Smoothie | B7: 4
A8: Sandwich | B8: 4
A9: Salad | B9: 5

Sheet SalesPivot
B2: Transcation Complete? | C2: Yes | J2: Transcation Complete? | K2: Yes
B3: Transaction Date | C3: (Multiple Items) | J3: Transaction Date | K3: (Multiple Items)
B4: Month | C4: (All) | J4: 2023 Sales Trend
B5: Monthly Sales | J5: Row Labels | K5: Sum of Total Spent
B6: Row Labels | C6: Sum of Total Spent | J6: Jan | K6: 7254
B7: 1 | C7: 2589.5 | J7: Feb | K7: 6644
B8: 2 | C8: 2688 | J8: Mar | K8: 7216
B9: 3 | C9: 2522 | J9: Apr | K9: 7179
B10: 4 | C10: 2759 | J10: May | K10: 6957.5
B11: 5 | C11: 2643 | J11: Jun | K11: 7353
B12: 6 | C12: 3482 | J12: Jul | K12: 6877.5
B13: 7 | C13: 2896 | J13: Aug | K13: 7112.5
B14: 8 | C14: 2774.5 | J14: Sep | K14: 6871
B15: 9 | C15: 2798 | J15: Oct | K15: 7314
B16: 10 | C16: 2978 | J16: Nov | K16: 6967
B17: 11 | C17: 2464 | J17: Dec | K17: 7177
B18: 12 | C18: 2620 | J18: Grand Total | K18: 84922.5
B19: 13 | C19: 2691.5
B20: 14 | C20: 2607.5
B21: 15 | C21: 2867.5
B22: 16 | C22: 3132.5
B23: 17 | C23: 2715.5 | I23: Transcation Complete? | J23: Yes
B24: 18 | C24: 2908.5 | I24: Transaction Date | J24: (Multiple Items)
B25: 19 | C25: 2775 | I25: Payment Method Comparison
B26: 20 | C26: 3001 | I26: Row Labels | J26: Total Sales
B27: 21 | C27: 3002.5 | I27: Cash | J27: 0.23344872
B28: 22 | C28: 2496 | I28: Credit Card | J28: 0.23474686
B29: 23 | C29: 3036 | I29: Digital Wallet | J29: 0.23766768
B30: 24 | C30: 2749.5 | I30: Unspecified | J30: 0.29413674
B31: 25 | C31: 2652.5 | I31: Grand Total | J31: 1 | N31: Transcation Complete? | O31: Yes
B32: 26 | C32: 2959.5 | N32: Transaction Date | O32: (Multiple Items)
B33: 27 | C33: 2470 | N33: 2023 Traffic Trend
B34: 28 | C34: 2974 | N34: Row Labels | O34: Count of Total Spent
B35: 29 | C35: 2380 | N35: Jan | O35: 818
B36: 30 | C36: 2726.5 | N36: Feb | O36: 727
B37: 31 | C37: 1563 | N37: Mar | O37: 827
B38: Grand Total | C38: 84922.5 | N38: Apr | O38: 774
N39: May | O39: 777
B40: Transcation Complete? | C40: Yes | N40: Jun | O40: 818
B41: Transaction Date | C41: (Multiple Items) | N41: Jul | O41: 791
B42: Month | C42: (All) | N42: Aug | O42: 803
B43: Average Daily Sales Patterns | N43: Sep | O43: 788
B44: Row Labels | C44: Sum of Total Spent | N44: Oct | O44: 838
B45: Sunday | C45: 13107.5 | N45: Nov | O45: 784
B46: Monday | C46: 14381 | N46: Dec | O46: 795
B47: Tuesday | C47: 12528 | N47: Grand Total | O47: 9540
B48: Wednesday | C48: 10784
B49: Thursday | C49: 10997.5
B50: Friday | C50: 11644.5
B51: Saturday | C51: 11480
B52: Grand Total | C52: 84922.5
B55: Transcation Complete? | C55: Yes
B56: Transaction Date | C56: (Multiple Items)
B57: Month | C57: (All)
B58: Location Preferences | I58: =6644/28 -> 237.28571
B59: Row Labels | C59: Total Sales
B60: In-store | C60: 0.31220785
B61: Takeaway | C61: 0.31405588
B62: Unspecified | C62: 0.37373628
B63: Grand Total | C63: 1
B72: Transcation Complete? | C72: Yes
B73: Transaction Date | C73: (Multiple Items)
B74: Month | C74: (All)
B75: Monthly Traffic
B76: Row Labels | C76: Count of Transcation Complete?
B77: 1 | C77: 296
B78: 2 | C78: 319
B79: 3 | C79: 285
B80: 4 | C80: 300
B81: 5 | C81: 301
B82: 6 | C82: 378
B83: 7 | C83: 323
B84: 8 | C84: 324
B85: 9 | C85: 315
B86: 10 | C86: 326
B87: 11 | C87: 271
B88: 12 | C88: 304
... B107: 31 | C107: 175
B108: Grand Total | C108: 9540
B110: Transcation Complete? | C110: Yes
B111: Transaction Date | C111: (Multiple Items)
B112: Month | C112: (All)
B113: Average Daily Traffic Patterns
B114: Row Labels | C114: Count of Transcation Complete?
B115: Sunday | C115: 1495
B116: Monday | C116: 1609
B117: Tuesday | C117: 1410
B118: Wednesday | C118: 1206
B119: Thursday | C119: 1245
B120: Friday | C120: 1284
B121: Saturday | C121: 1291
B122: Grand Total | C122: 9540

Sheet ItemPivot
B1: Month | C1: Jan | S1: Month | T1: Jan
B2: Monthly Item Sales Volume | S2: Monthly Item Sales Amount
B3: Row Labels | C3: Sum of Quantity | S3: Row Labels | T3: Sales Amount
B4: Cake | C4: 285 | S4: Cake | T4: 855
B5: Coffee | C5: 296 | S5: Coffee | T5: 592
B6: Cookie | C6: 292 | S6: Cookie | T6: 292
B7: Juice | C7: 306 | S7: Juice | T7: 918
B8: Salad | C8: 333 | S8: Salad | T8: 1665
B9: Sandwich | C9: 346 | S9: Sandwich | T9: 1384
B10: Smoothie | C10: 189 | S10: Smoothie | T10: 756
B11: Tea | C11: 304 | S11: Tea | T11: 456
B12: Grand Total | C12: 2351 | S12: Grand Total | T12: 6918
B20: Item | C20: Cake
B21: Item Sales by Month
B22: Row Labels | C22: Sum of Quantity
B23: Jan | C23: 17
B24: Feb | C24: 11
B25: Mar | C25: 27
B26: Apr | C26: 13
B27: May | C27: 13
B28: Jun | C28: 16
B29: Jul | C29: 26
B30: Aug | C30: 11
B31: Sep | C31: 17
B32: Oct | C32: 19
B33: Nov | C33: 21
B34: Dec | C34: 18
B35: Grand Total | C35: 209
B53: Transcation Complete? | C53: Yes
B54: Transaction Date | C54: (Multiple Items)
B55: Average items purchase
B56: Row Labels | C56: Average of Quantity
B57: Cake | C57: 0.9952381
B58: Coffee | C58: 1.4796748
B59: Cookie | C59: 2.9774109
B60: Juice | C60: 0.98623853
B61: Salad | C61: 0.99212598
B62: Sandwich | C62: 0.98095238
B63: Smoothie | C63: 0.99009901
B64: Tea | C64: 2.027417
B65: Grand Total | C65: 1.9364431
B67: Transcation Complete? | C67: Yes
B68: Transaction Date | C68: (Multiple Items)
B69: Item Purchase Distribution
B70: Row Labels | C70: Sum of Quantity
B71: Cake | C71: 0.045762712
B72: Coffee | C72: 0.091525424
B73: Cookie | C73: 0.51016949
B74: Juice | C74: 0.038983051
B75: Salad | C75: 0.030508475
B76: Sandwich | C76: 0.023728814
B77: Smoothie | C77: 0.030508475
B78: Tea | C78: 0.22881356
B79: Grand Total | C79: 1
B83: Transcation Complete? | C83: Yes
B84: Transaction Date | C84: (Multiple Items)
B85: Average items purchase per transcation
B86: Row Labels | C86: Average of Quantity
B87: Cake | C87: 3.0295749
B88: Coffee | C88: 3.0224719
B89: Cookie | C89: 2.9774109
B90: Juice | C90: 2.9724199
B91: Salad | C91: 2.9967105
B92: Sandwich | C92: 3.0390698
B93: Smoothie | C93: 3.0477099
B94: Tea | C94: 3.0131349
B95: Unspecified | C95: 3.0614035
B96: Grand Total | C96: 3.0140461

Sheet Dashboard_sales
A1: 2023 Café sales Report
A2: Total Revenue | B2: Average Monthly Sales | C2: Average Daily Sales
A3: $89060.00 | B3: $7421.67 | C3: $244.00
A18: Month | B18: Avgerage Daily Sales | C18: Average Daily Traffic
A19: January | B19: 234 | C19: 26.387097
A20: February | B20: 237.28571 | C20: 25.964286
A21: March | B21: 232.77419 | C21: 26.677419
A22: April | B22: 239.3 | C22: 25.8
A23: May | B23: 224.43548 | C23: 25.064516
A24: June | B24: 245.1 | C24: 27.266667
A25: July | B25: 221.85484 | C25: 25.516129
A26: August | B26: 229.43548 | C26: 25.903226
A27: September | B27: 229.03333 | C27: 26.266667
A28: October | B28: 235.93548 | C28: 27.032258
A29: November | B29: 232.23333 | C29: 26.133333
A30: December | B30: 231.51613 | C30: 25.645161
V37: =153/3 -> 51

Sheet Dashboard_spendinghabit
A1: 2023 Café Spending Habit Report
A2: Best Seller | C2: Highest Sales Item
A3: Coffee | C3: Salad
A11: Spend Group Percentage | C11: Average items purchase per transcation
A12: Spent Group | B12: Percentage | C12: Spent Group | D12: Percentage
A13: $1-5 | B13: 0.36792453 | C13: $1-5 | D13: 1.917094
A14: $6-10 | B14: 0.30503145 | C14: $6-10 | D14: 3.0841924
A15: $11-15 | B15: 0.17400419 | C15: $11-15 | D15: 3.8843373
A16: $16-20 | B16: 0.12578616 | C16: $16-20 | D16: 4.4225
A17: $20+ | B17: 0.027253669 | C17: $20+ | D17: 4.9807692
